rtl/Cores/Divisor/Control_Divisor.v
module Control_Divisor (

    input  wire clk,
    input  wire rst,
    input  wire init,
    input  wire MSB_r,
    input  wire i,

    output reg  LD,
    output reg  SH,
    output reg  EN_Resta,
    output reg  EN_C,
    output reg  bit_c,
    output reg  DEC,
    output reg  DONE

);

    parameter START   = 3'b000;
    parameter SHIFT   = 3'b001;
    parameter RESTA   = 3'b010;
    parameter BIT_0   = 3'b011;
    parameter BIT_1   = 3'b100;
    parameter CHECK_I = 3'b101;
    parameter END1    = 3'b110;

    reg [2:0] state;

    always @(posedge clk or posedge rst) begin

        if (rst) begin
            state <= START;
        end

        else begin

            case (state)

                START: begin
                    if (init)
                        state <= SHIFT;
                    else
                        state <= START;
                end

                SHIFT: begin
                    state <= RESTA;
                end

                RESTA: begin
                    if (MSB_r)
                        state <= BIT_0;
                    else
                        state <= BIT_1;
                end

                BIT_0: begin
                    state <= CHECK_I;
                end

                BIT_1: begin
                    state <= CHECK_I;
                end

                CHECK_I: begin
                    if (i)
                        state <= SHIFT;
                    else
                        state <= END1;
                end

                END1: begin
                    state <= START;
                end

                default: begin
                    state <= START;
                end

            endcase

        end

    end

    always @(*) begin

        LD       = 0;
        SH       = 0;
        EN_Resta = 0;
        EN_C     = 0;
        bit_c    = 0;
        DEC      = 0;
        DONE     = 0;

        case (state)

            START: begin
                LD = 1;
            end

            SHIFT: begin
                SH  = 1;
                DEC = 1;
            end

            RESTA: begin
            end

            BIT_0: begin
                EN_C  = 1;
                bit_c = 0;
            end

            BIT_1: begin
                EN_C     = 1;
                bit_c    = 1;
                EN_Resta = 1;
            end

            CHECK_I: begin
            end

            END1: begin
                DONE = 1;
            end

        endcase

    end

endmodule

rtl/Cores/Divisor/Comp_count_Divisor.v
module Comp_count_Divisor (

    input [5:0] count_out,

    output i

);

    assign i = (count_out != 6'd0);

endmodule

rtl/Cores/Divisor/Count_Divisior.v
module Count_Divisor (

    input clk,
    input LD,
    input DEC,

    output reg [5:0] count_out

);

    always @(posedge clk) begin

        if (LD) begin
            count_out <= 6'd32;
        end

        else if (DEC) begin
            count_out <= count_out - 1;
        end

    end

endmodule

rtl/Cores/Divisor/Resultado.v
module Resultado #(
    parameter width = 31
)(
    input  wire clk,
    input  wire rst,
    input  wire LD,
    input  wire EN_C,
    input  wire bit_c,

    output reg [width:0] Resultado_out
);

    always @(posedge clk) begin

        if (rst) begin
            Resultado_out <= 0;
        end

        else begin

            if (LD) begin
                Resultado_out <= 0;
            end

            else if (EN_C) begin
                Resultado_out <= {Resultado_out[width-1:0], bit_c};
            end

        end

    end

endmodule

Calculadora/rtl/Cores/Divisor/Restador.v
module Restador_Divisor #(
    parameter width = 31
)(
    input  wire [width:0] A,
    input  wire [width:0] B,

    output wire [width:0] Resta_out,
    output wire           MSB_r
);

    assign Resta_out = A - B;

    assign MSB_r = Resta_out[width];

endmodule

rtl/Cores/Divisor/vAux.v
module vAux #(
    parameter width = 31
)(
    input  wire           clk,
    input  wire           rst,
    input  wire           LD,
    input  wire           SH,
    input  wire           EN_Resta,
    input  wire           MSB_A,
    input  wire [width:0] Resta_in,

    output reg  [width:0] vAux_out
);

    always @(posedge clk) begin

        if (rst) begin
            vAux_out <= 0;
        end

        else begin

            if (LD) begin
                vAux_out <= 0;
            end

            else if (SH) begin
                vAux_out <= {vAux_out[width-1:0], MSB_A};
            end

            else if (EN_Resta) begin
                vAux_out <= Resta_in;
            end

        end

    end

endmodule

rtl/Cores/Divisor/B_process_Divisor.v
module B_process_Divisor #(
    parameter width = 31
)(
    input  wire           clk,
    input  wire           rst,
    input  wire           LD,
    input  wire [width:0] DR,

    output reg [width:0] B_out
);

    always @(posedge clk) begin

        if (rst) begin
            B_out <= 0;
        end

        else begin

            if (LD) begin
                B_out <= DR;
            end

        end

    end

endmodule

rtl/Cores/Divisor/A_process_Divisor.v
module A_process_Divisor #(
    parameter width = 31
)(
    input  wire             clk,
    input  wire             rst,
    input  wire             LD,
    input  wire             SH,
    input  wire [width:0]   Dividendo,

    output wire             MSB_A,
    output reg  [width:0]   A_out
);

    always @(posedge clk) begin

        if (rst) begin
            A_out <= 0;
        end

        else begin

            if (LD) begin
                A_out <= Dividendo;
            end

            else if (SH) begin
                A_out <= A_out << 1;
            end

        end

    end

    assign MSB_A = A_out[width];

endmodule

Calculadora/rtl/Cores/Divisor/TOP_Divisor.v
module TOP_Divisor #(
    parameter width = 31
)(
    input  wire           clk,
    input  wire           rst,
    input  wire           init,
    input  wire [width:0] Dividendo,
    input  wire [width:0] DR,

    output wire [width:0] Residuo,
    output wire [width:0] Resultado,
    output wire           DONE
);

    wire LD;
    wire SH;
    wire EN_Resta;
    wire EN_C;
    wire bit_c;
    wire DEC;

    wire MSB_A;
    wire MSB_r;
    wire i;

    wire [width:0] A_out;
    wire [width:0] B_out;
    wire [width:0] vAux_out;
    wire [width:0] Resta_out;
    wire [5:0]     count_out;

    A_process_Divisor #(
        .width(width)
    ) A_process_inst (
        .clk(clk),
        .rst(rst),
        .LD(LD),
        .SH(SH),
        .Dividendo(Dividendo),
        .A_out(A_out),
        .MSB_A(MSB_A)
    );

    B_process_Divisor #(
        .width(width)
    ) B_process_inst (
        .clk(clk),
        .rst(rst),
        .LD(LD),
        .DR(DR),
        .B_out(B_out)
    );

    vAux #(
        .width(width)
    ) vAux_inst (
        .clk(clk),
        .rst(rst),
        .LD(LD),
        .SH(SH),
        .EN_Resta(EN_Resta),
        .MSB_A(MSB_A),
        .Resta_in(Resta_out),
        .vAux_out(vAux_out)
    );

    Restador_Divisor #(
        .width(width)
    ) Restador_inst (
        .A(vAux_out),
        .B(B_out),
        .Resta_out(Resta_out),
        .MSB_r(MSB_r)
    );

    Resultado #(
        .width(width)
    ) Resultado_inst (
        .clk(clk),
        .rst(rst),
        .LD(LD),
        .EN_C(EN_C),
        .bit_c(bit_c),
        .Resultado_out(Resultado)
    );

    Count_Divisor Count_inst (
        .clk(clk),
        .LD(LD),
        .DEC(DEC),
        .count_out(count_out)
    );

    Comp_count_Divisor Comp_count_inst (
        .count_out(count_out),
        .i(i)
    );

    Control_Divisor control_inst (
        .clk(clk),
        .rst(rst),
        .init(init),
        .MSB_r(MSB_r),
        .i(i),
        .LD(LD),
        .SH(SH),
        .EN_Resta(EN_Resta),
        .EN_C(EN_C),
        .bit_c(bit_c),
        .DEC(DEC),
        .DONE(DONE)
    );

    assign Residuo = vAux_out;

endmodule

rtl/Cores/Divisor/Periferico_Divisor.v
module Periferico_Divisor (
    input clk,
    input reset,

    input [31:0] d_in,
    input cs,
    input [4:0] addr,
    input rd,
    input wr,

    output reg [31:0] d_out
);

    reg [5:0] s;

    reg [31:0] Dividendo;
    reg [31:0] DR;
    reg init;

    wire [31:0] Residuo_wire;
    wire [31:0] Resultado_wire;
    wire DONE_wire;

    reg [31:0] Residuo_reg;
    reg [31:0] Resultado_reg;
    reg DONE_reg;

    always @(*) begin
        if (cs) begin
            case (addr)
                5'h04: s = 6'b000001; // Dividendo
                5'h08: s = 6'b000010; // DR
                5'h0C: s = 6'b000100; // init
                5'h10: s = 6'b001000; // Resultado
                5'h14: s = 6'b010000; // Residuo
                5'h18: s = 6'b100000; // DONE
                default: s = 6'b000000;
            endcase
        end
        else begin
            s = 6'b000000;
        end
    end

    always @(posedge clk) begin
        if (reset) begin
            Dividendo     <= 32'b0;
            DR            <= 32'b0;
            init          <= 1'b0;
            Resultado_reg <= 32'b0;
            Residuo_reg   <= 32'b0;
            DONE_reg      <= 1'b0;
        end
        else begin
            if (cs && wr) begin
                if (s[0])
                    Dividendo <= d_in;

                if (s[1])
                    DR <= d_in;

                if (s[2]) begin
                    init <= d_in[0];

                    if (d_in[0] == 1'b1) begin
                        DONE_reg      <= 1'b0;
                        Resultado_reg <= 32'b0;
                        Residuo_reg   <= 32'b0;
                    end
                end
            end

            if (DONE_wire) begin
                Resultado_reg <= Resultado_wire;
                Residuo_reg   <= Residuo_wire;
                DONE_reg      <= 1'b1;
            end
        end
    end

    always @(*) begin
        if (reset) begin
            d_out = 32'b0;
        end
        else if (cs && rd) begin
            case (s)
                6'b001000: d_out = Resultado_reg;
                6'b010000: d_out = Residuo_reg;
                6'b100000: d_out = {31'b0, DONE_reg};
                default:   d_out = 32'b0;
            endcase
        end
        else begin
            d_out = 32'b0;
        end
    end

    TOP_Divisor #(
        .width(31)
    ) u_div (
        .clk(clk),
        .rst(reset),
        .init(init),
        .Dividendo(Dividendo),
        .DR(DR),
        .Residuo(Residuo_wire),
        .Resultado(Resultado_wire),
        .DONE(DONE_wire)
    );

endmodule

rtl/Cores/Divisor/Testbench_Periferico_Divisor.v
`timescale 1ns/1ps

module Testbench_Periferico_Divisor;

    reg clk;
    reg reset;
    reg [31:0] d_in;
    reg cs;
    reg [4:0] addr;
    reg rd;
    reg wr;

    wire [31:0] d_out;

    Periferico_Divisor DUT (
        .clk(clk),
        .reset(reset),
        .d_in(d_in),
        .cs(cs),
        .addr(addr),
        .rd(rd),
        .wr(wr),
        .d_out(d_out)
    );

    always #5 clk = ~clk;

    task escribir;
        input [4:0] direccion;
        input [31:0] dato;
        begin
            @(negedge clk);
            cs   = 1;
            wr   = 1;
            rd   = 0;
            addr = direccion;
            d_in = dato;

            @(negedge clk);
            wr = 0;
        end
    endtask

    task leer;
        input [4:0] direccion;
        begin
            @(negedge clk);
            cs   = 1;
            rd   = 1;
            wr   = 0;
            addr = direccion;

            #1;
        end
    endtask

    initial begin

        $dumpfile("Periferico_Divisor.vcd");
        $dumpvars(0, Testbench_Periferico_Divisor);

        clk   = 0;
        reset = 1;
        d_in  = 0;
        cs    = 0;
        addr  = 0;
        rd    = 0;
        wr    = 0;

        #20;
        reset = 0;

        // =========================
        // Operacion 1: 100 / 12
        // Esperado: cociente 8, residuo 4
        // =========================

        escribir(5'h04, 32'd100);
        escribir(5'h08, 32'd12);

        escribir(5'h0C, 32'd1);
        escribir(5'h0C, 32'd0);

        wait(DUT.DONE_reg);

        leer(5'h18);
        $display("Operacion 1 - DONE = %d", d_out);

        leer(5'h10);
        $display("Operacion 1 - Resultado / Cociente = %d", d_out);

        leer(5'h14);
        $display("Operacion 1 - Residuo = %d", d_out);

        // =========================
        // Operacion 2: 25 / 5
        // Esperado: cociente 5, residuo 0
        // Sin resetear el sistema
        // =========================

        escribir(5'h04, 32'd25);
        escribir(5'h08, 32'd5);

        escribir(5'h0C, 32'd1);

        #1;
        $display("Despues de nuevo init=1:");
        $display("DONE_reg      = %d", DUT.DONE_reg);
        $display("Resultado_reg = %d", DUT.Resultado_reg);
        $display("Residuo_reg   = %d", DUT.Residuo_reg);

        escribir(5'h0C, 32'd0);

        wait(DUT.DONE_reg);

        leer(5'h18);
        $display("Operacion 2 - DONE = %d", d_out);

        leer(5'h10);
        $display("Operacion 2 - Resultado / Cociente = %d", d_out);

        leer(5'h14);
        $display("Operacion 2 - Residuo = %d", d_out);

        rd = 0;
        cs = 0;

        #20;
        $finish;

    end

endmodule

//iverilog -s Testbench_Periferico_Divisor -o sim *.v
//gtkwave Periferico_Divisor.vcd

rtl/Cores/Divisor/Periferico_Divisor.vcd
$date
	Wed Jun 10 23:35:51 2026
$end
$version
	Icarus Verilog
$end
$timescale
	1ps
$end
$scope module Testbench_Periferico_Divisor $end
$var wire 32 ! d_out [31:0] $end
$var reg 5 " addr [4:0] $end
$var reg 1 # clk $end
$var reg 1 $ cs $end
$var reg 32 % d_in [31:0] $end
$var reg 1 & rd $end
$var reg 1 ' reset $end
$var reg 1 ( wr $end
$scope module DUT $end
$var wire 5 ) addr [4:0] $end
$var wire 1 # clk $end
$var wire 1 $ cs $end
$var wire 32 * d_in [31:0] $end
$var wire 1 & rd $end
$var wire 1 ' reset $end
$var wire 1 ( wr $end
$var wire 32 + Resultado_wire [31:0] $end
$var wire 32 , Residuo_wire [31:0] $end
$var wire 1 - DONE_wire $end
$var reg 1 . DONE_reg $end
$var reg 32 / DR [31:0] $end
$var reg 32 0 Dividendo [31:0] $end
$var reg 32 1 Residuo_reg [31:0] $end
$var reg 32 2 Resultado_reg [31:0] $end
$var reg 32 3 d_out [31:0] $end
$var reg 1 4 init $end
$var reg 6 5 s [5:0] $end
$scope module u_div $end
$var wire 32 6 DR [31:0] $end
$var wire 32 7 Dividendo [31:0] $end
$var wire 32 8 Residuo [31:0] $end
$var wire 1 # clk $end
$var wire 1 4 init $end
$var wire 1 ' rst $end
$var wire 32 9 vAux_out [31:0] $end
$var wire 1 : i $end
$var wire 6 ; count_out [5:0] $end
$var wire 1 < bit_c $end
$var wire 1 = SH $end
$var wire 32 > Resultado [31:0] $end
$var wire 32 ? Resta_out [31:0] $end
$var wire 1 @ MSB_r $end
$var wire 1 A MSB_A $end
$var wire 1 B LD $end
$var wire 1 C EN_Resta $end
$var wire 1 D EN_C $end
$var wire 1 - DONE $end
$var wire 1 E DEC $end
$var wire 32 F B_out [31:0] $end
$var wire 32 G A_out [31:0] $end
$var parameter 32 H width $end
$scope module A_process_inst $end
$var wire 32 I Dividendo [31:0] $end
$var wire 1 # clk $end
$var wire 1 ' rst $end
$var wire 1 = SH $end
$var wire 1 A MSB_A $end
$var wire 1 B LD $end
$var parameter 32 J width $end
$var reg 32 K A_out [31:0] $end
$upscope $end
$scope module B_process_inst $end
$var wire 32 L DR [31:0] $end
$var wire 1 # clk $end
$var wire 1 ' rst $end
$var wire 1 B LD $end
$var parameter 32 M width $end
$var reg 32 N B_out [31:0] $end
$upscope $end
$scope module Comp_count_inst $end
$var wire 1 : i $end
$var wire 6 O count_out [5:0] $end
$upscope $end
$scope module Count_inst $end
$var wire 1 # clk $end
$var wire 1 B LD $end
$var wire 1 E DEC $end
$var reg 6 P count_out [5:0] $end
$upscope $end
$scope module Restador_inst $end
$var wire 32 Q B [31:0] $end
$var wire 32 R Resta_out [31:0] $end
$var wire 1 @ MSB_r $end
$var wire 32 S A [31:0] $end
$var parameter 32 T width $end
$upscope $end
$scope module Resultado_inst $end
$var wire 1 # clk $end
$var wire 1 ' rst $end
$var wire 1 < bit_c $end
$var wire 1 B LD $end
$var wire 1 D EN_C $end
$var parameter 32 U width $end
$var reg 32 V Resultado_out [31:0] $end
$upscope $end
$scope module control_inst $end
$var wire 1 @ MSB_r $end
$var wire 1 # clk $end
$var wire 1 : i $end
$var wire 1 4 init $end
$var wire 1 ' rst $end
$var parameter 3 W BIT_0 $end
$var parameter 3 X BIT_1 $end
$var parameter 3 Y CHECK_I $end
$var parameter 3 Z END1 $end
$var parameter 3 [ RESTA $end
$var parameter 3 \ SHIFT $end
$var parameter 3 ] START $end
$var reg 1 E DEC $end
$var reg 1 - DONE $end
$var reg 1 D EN_C $end
$var reg 1 C EN_Resta $end
$var reg 1 B LD $end
$var reg 1 = SH $end
$var reg 1 < bit_c $end
$var reg 3 ^ state [2:0] $end
$upscope $end
$scope module vAux_inst $end
$var wire 1 C EN_Resta $end
$var wire 1 B LD $end
$var wire 1 A MSB_A $end
$var wire 32 _ Resta_in [31:0] $end
$var wire 1 = SH $end
$var wire 1 # clk $end
$var wire 1 ' rst $end
$var parameter 32 ` width $end
$var reg 32 a vAux_out [31:0] $end
$upscope $end
$upscope $end
$upscope $end
$scope task escribir $end
$var reg 32 b dato [31:0] $end
$var reg 5 c direccion [4:0] $end
$upscope $end
$scope task leer $end
$var reg 5 d direccion [4:0] $end
$upscope $end
$upscope $end
$enddefinitions $end
$comment Show the parameter values. $end
$dumpall
b11111 `
b0 ]
b1 \
b10 [
b110 Z
b101 Y
b100 X
b11 W
b11111 U
b11111 T
b11111 M
b11111 J
b11111 H
$end
#0
$dumpvars
bx d
bx c
bx b
bx a
bx _
b0 ^
bx V
bx S
bx R
bx Q
bx P
bx O
bx N
bx L
bx K
bx I
bx G
bx F
0E
0D
0C
1B
xA
x@
bx ?
bx >
0=
0<
bx ;
x:
bx 9
bx 8
bx 7
bx 6
b0 5
x4
b0 3
bx 2
bx 1
bx 0
bx /
x.
0-
bx ,
bx +
b0 *
b0 )
0(
1'
0&
b0 %
0$
0#
b0 "
b0 !
$end
#5000
0A
0@
b0 G
b0 K
b0 ?
b0 R
b0 _
b0 F
b0 N
b0 Q
b0 ,
b0 8
b0 9
b0 S
b0 a
b0 +
b0 >
b0 V
1:
b100000 ;
b100000 O
b100000 P
0.
b0 1
b0 2
04
b0 /
b0 6
b0 L
b0 0
b0 7
b0 I
1#
#10000
0#
#15000
1#
#20000
b1 5
b1100100 %
b1100100 *
b100 "
b100 )
1(
1$
0#
b1100100 b
b100 c
0'
#25000
b1100100 0
b1100100 7
b1100100 I
1#
#30000
b1100 b
b1000 c
0(
0#
#35000
b1100100 G
b1100100 K
1#
#40000
b10 5
b1100 %
b1100 *
b1000 "
b1000 )
1(
0#
#45000
b1100 /
b1100 6
b1100 L
1#
#50000
b1 b
b1100 c
0(
0#
#55000
1@
b11111111111111111111111111110100 ?
b11111111111111111111111111110100 R
b11111111111111111111111111110100 _
b1100 F
b1100 N
b1100 Q
1#
#60000
b100 5
b1 %
b1 *
b1100 "
b1100 )
1(
0#
#65000
14
1#
#70000
b0 b
0(
0#
#75000
1E
1=
0B
b1 ^
1#
#80000
b0 %
b0 *
1(
0#
#85000
0E
0=
b11001000 G
b11001000 K
b11111 ;
b11111 O
b11111 P
04
b10 ^
1#
#90000
0(
0#
#95000
1D
b11 ^
1#
#100000
0#
#105000
0D
b101 ^
1#
#110000
0#
#115000
1E
1=
b1 ^
1#
#120000
0#
#125000
0E
0=
b110010000 G
b110010000 K
b11110 ;
b11110 O
b11110 P
b10 ^
1#
#130000
0#
#135000
1D
b11 ^
1#
#140000
0#
#145000
0D
b101 ^
1#
#150000
0#
#155000
1E
1=
b1 ^
1#
#160000
0#
#165000
0E
0=
b1100100000 G
b1100100000 K
b11101 ;
b11101 O
b11101 P
b10 ^
1#
#170000
0#
#175000
1D
b11 ^
1#
#180000
0#
#185000
0D
b101 ^
1#
#190000
0#
#195000
1E
1=
b1 ^
1#
#200000
0#
#205000
0E
0=
b11001000000 G
b11001000000 K
b11100 ;
b11100 O
b11100 P
b10 ^
1#
#210000
0#
#215000
1D
b11 ^
1#
#220000
0#
#225000
0D
b101 ^
1#
#230000
0#
#235000
1E
1=
b1 ^
1#
#240000
0#
#245000
0E
0=
b110010000000 G
b110010000000 K
b11011 ;
b11011 O
b11011 P
b10 ^
1#
#250000
0#
#255000
1D
b11 ^
1#
#260000
0#
#265000
0D
b101 ^
1#
#270000
0#
#275000
1E
1=
b1 ^
1#
#280000
0#
#285000
0E
0=
b1100100000000 G
b1100100000000 K
b11010 ;
b11010 O
b11010 P
b10 ^
1#
#290000
0#
#295000
1D
b11 ^
1#
#300000
0#
#305000
0D
b101 ^
1#
#310000
0#
#315000
1E
1=
b1 ^
1#
#320000
0#
#325000
0E
0=
b11001000000000 G
b11001000000000 K
b11001 ;
b11001 O
b11001 P
b10 ^
1#
#330000
0#
#335000
1D
b11 ^
1#
#340000
0#
#345000
0D
b101 ^
1#
#350000
0#
#355000
1E
1=
b1 ^
1#
#360000
0#
#365000
0E
0=
b110010000000000 G
b110010000000000 K
b11000 ;
b11000 O
b11000 P
b10 ^
1#
#370000
0#
#375000
1D
b11 ^
1#
#380000
0#
#385000
0D
b101 ^
1#
#390000
0#
#395000
1E
1=
b1 ^
1#
#400000
0#
#405000
0E
0=
b1100100000000000 G
b1100100000000000 K
b10111 ;
b10111 O
b10111 P
b10 ^
1#
#410000
0#
#415000
1D
b11 ^
1#
#420000
0#
#425000
0D
b101 ^
1#
#430000
0#
#435000
1E
1=
b1 ^
1#
#440000
0#
#445000
0E
0=
b11001000000000000 G
b11001000000000000 K
b10110 ;
b10110 O
b10110 P
b10 ^
1#
#450000
0#
#455000
1D
b11 ^
1#
#460000
0#
#465000
0D
b101 ^
1#
#470000
0#
#475000
1E
1=
b1 ^
1#
#480000
0#
#485000
0E
0=
b110010000000000000 G
b110010000000000000 K
b10101 ;
b10101 O
b10101 P
b10 ^
1#
#490000
0#
#495000
1D
b11 ^
1#
#500000
0#
#505000
0D
b101 ^
1#
#510000
0#
#515000
1E
1=
b1 ^
1#
#520000
0#
#525000
0E
0=
b1100100000000000000 G
b1100100000000000000 K
b10100 ;
b10100 O
b10100 P
b10 ^
1#
#530000
0#
#535000
1D
b11 ^
1#
#540000
0#
#545000
0D
b101 ^
1#
#550000
0#
#555000
1E
1=
b1 ^
1#
#560000
0#
#565000
0E
0=
b11001000000000000000 G
b11001000000000000000 K
b10011 ;
b10011 O
b10011 P
b10 ^
1#
#570000
0#
#575000
1D
b11 ^
1#
#580000
0#
#585000
0D
b101 ^
1#
#590000
0#
#595000
1E
1=
b1 ^
1#
#600000
0#
#605000
0E
0=
b110010000000000000000 G
b110010000000000000000 K
b10010 ;
b10010 O
b10010 P
b10 ^
1#
#610000
0#
#615000
1D
b11 ^
1#
#620000
0#
#625000
0D
b101 ^
1#
#630000
0#
#635000
1E
1=
b1 ^
1#
#640000
0#
#645000
0E
0=
b1100100000000000000000 G
b1100100000000000000000 K
b10001 ;
b10001 O
b10001 P
b10 ^
1#
#650000
0#
#655000
1D
b11 ^
1#
#660000
0#
#665000
0D
b101 ^
1#
#670000
0#
#675000
1E
1=
b1 ^
1#
#680000
0#
#685000
0E
0=
b11001000000000000000000 G
b11001000000000000000000 K
b10000 ;
b10000 O
b10000 P
b10 ^
1#
#690000
0#
#695000
1D
b11 ^
1#
#700000
0#
#705000
0D
b101 ^
1#
#710000
0#
#715000
1E
1=
b1 ^
1#
#720000
0#
#725000
0E
0=
b110010000000000000000000 G
b110010000000000000000000 K
b1111 ;
b1111 O
b1111 P
b10 ^
1#
#730000
0#
#735000
1D
b11 ^
1#
#740000
0#
#745000
0D
b101 ^
1#
#750000
0#
#755000
1E
1=
b1 ^
1#
#760000
0#
#765000
0E
0=
b1100100000000000000000000 G
b1100100000000000000000000 K
b1110 ;
b1110 O
b1110 P
b10 ^
1#
#770000
0#
#775000
1D
b11 ^
1#
#780000
0#
#785000
0D
b101 ^
1#
#790000
0#
#795000
1E
1=
b1 ^
1#
#800000
0#
#805000
0E
0=
b11001000000000000000000000 G
b11001000000000000000000000 K
b1101 ;
b1101 O
b1101 P
b10 ^
1#
#810000
0#
#815000
1D
b11 ^
1#
#820000
0#
#825000
0D
b101 ^
1#
#830000
0#
#835000
1E
1=
b1 ^
1#
#840000
0#
#845000
0E
0=
b110010000000000000000000000 G
b110010000000000000000000000 K
b1100 ;
b1100 O
b1100 P
b10 ^
1#
#850000
0#
#855000
1D
b11 ^
1#
#860000
0#
#865000
0D
b101 ^
1#
#870000
0#
#875000
1E
1=
b1 ^
1#
#880000
0#
#885000
0E
0=
b1100100000000000000000000000 G
b1100100000000000000000000000 K
b1011 ;
b1011 O
b1011 P
b10 ^
1#
#890000
0#
#895000
1D
b11 ^
1#
#900000
0#
#905000
0D
b101 ^
1#
#910000
0#
#915000
1E
1=
b1 ^
1#
#920000
0#
#925000
0E
0=
b11001000000000000000000000000 G
b11001000000000000000000000000 K
b1010 ;
b1010 O
b1010 P
b10 ^
1#
#930000
0#
#935000
1D
b11 ^
1#
#940000
0#
#945000
0D
b101 ^
1#
#950000
0#
#955000
1E
1=
b1 ^
1#
#960000
0#
#965000
0E
0=
b110010000000000000000000000000 G
b110010000000000000000000000000 K
b1001 ;
b1001 O
b1001 P
b10 ^
1#
#970000
0#
#975000
1D
b11 ^
1#
#980000
0#
#985000
0D
b101 ^
1#
#990000
0#
#995000
1E
1=
b1 ^
1#
#1000000
0#
#1005000
0E
0=
b1100100000000000000000000000000 G
b1100100000000000000000000000000 K
b1000 ;
b1000 O
b1000 P
b10 ^
1#
#1010000
0#
#1015000
1D
b11 ^
1#
#1020000
0#
#1025000
0D
b101 ^
1#
#1030000
0#
#1035000
1E
1=
b1 ^
1#
#1040000
0#
#1045000
1A
0E
0=
b11001000000000000000000000000000 G
b11001000000000000000000000000000 K
b111 ;
b111 O
b111 P
b10 ^
1#
#1050000
0#
#1055000
1D
b11 ^
1#
#1060000
0#
#1065000
0D
b101 ^
1#
#1070000
0#
#1075000
1E
1=
b1 ^
1#
#1080000
0#
#1085000
0E
0=
b10010000000000000000000000000000 G
b10010000000000000000000000000000 K
b11111111111111111111111111110101 ?
b11111111111111111111111111110101 R
b11111111111111111111111111110101 _
b1 ,
b1 8
b1 9
b1 S
b1 a
b110 ;
b110 O
b110 P
b10 ^
1#
#1090000
0#
#1095000
1D
b11 ^
1#
#1100000
0#
#1105000
0D
b101 ^
1#
#1110000
0#
#1115000
1E
1=
b1 ^
1#
#1120000
0#
#1125000
0A
0E
0=
b100000000000000000000000000000 G
b100000000000000000000000000000 K
b11111111111111111111111111110111 ?
b11111111111111111111111111110111 R
b11111111111111111111111111110111 _
b11 ,
b11 8
b11 9
b11 S
b11 a
b101 ;
b101 O
b101 P
b10 ^
1#
#1130000
0#
#1135000
1D
b11 ^
1#
#1140000
0#
#1145000
0D
b101 ^
1#
#1150000
0#
#1155000
1E
1=
b1 ^
1#
#1160000
0#
#1165000
0E
0=
b1000000000000000000000000000000 G
b1000000000000000000000000000000 K
b11111111111111111111111111111010 ?
b11111111111111111111111111111010 R
b11111111111111111111111111111010 _
b110 ,
b110 8
b110 9
b110 S
b110 a
b100 ;
b100 O
b100 P
b10 ^
1#
#1170000
0#
#1175000
1D
b11 ^
1#
#1180000
0#
#1185000
0D
b101 ^
1#
#1190000
0#
#1195000
1E
1=
b1 ^
1#
#1200000
0#
#1205000
1A
0@
0E
0=
b10000000000000000000000000000000 G
b10000000000000000000000000000000 K
b0 ?
b0 R
b0 _
b1100 ,
b1100 8
b1100 9
b1100 S
b1100 a
b11 ;
b11 O
b11 P
b10 ^
1#
#1210000
0#
#1215000
1C
1<
1D
b100 ^
1#
#1220000
0#
#1225000
1@
0<
0D
0C
b11111111111111111111111111110100 ?
b11111111111111111111111111110100 R
b11111111111111111111111111110100 _
b0 ,
b0 8
b0 9
b0 S
b0 a
b1 +
b1 >
b1 V
b101 ^
1#
#1230000
0#
#1235000
1E
1=
b1 ^
1#
#1240000
0#
#1245000
0A
0E
0=
b0 G
b0 K
b11111111111111111111111111110101 ?
b11111111111111111111111111110101 R
b11111111111111111111111111110101 _
b1 ,
b1 8
b1 9
b1 S
b1 a
b10 ;
b10 O
b10 P
b10 ^
1#
#1250000
0#
#1255000
1D
b11 ^
1#
#1260000
0#
#1265000
0D
b10 +
b10 >
b10 V
b101 ^
1#
#1270000
0#
#1275000
1E
1=
b1 ^
1#
#1280000
0#
#1285000
0E
0=
b11111111111111111111111111110110 ?
b11111111111111111111111111110110 R
b11111111111111111111111111110110 _
b10 ,
b10 8
b10 9
b10 S
b10 a
b1 ;
b1 O
b1 P
b10 ^
1#
#1290000
0#
#1295000
1D
b11 ^
1#
#1300000
0#
#1305000
0D
b100 +
b100 >
b100 V
b101 ^
1#
#1310000
0#
#1315000
1E
1=
b1 ^
1#
#1320000
0#
#1325000
0E
0=
b11111111111111111111111111111000 ?
b11111111111111111111111111111000 R
b11111111111111111111111111111000 _
b100 ,
b100 8
b100 9
b100 S
b100 a
0:
b0 ;
b0 O
b0 P
b10 ^
1#
#1330000
0#
#1335000
1D
b11 ^
1#
#1340000
0#
#1345000
0D
b1000 +
b1000 >
b1000 V
b101 ^
1#
#1350000
0#
#1355000
1-
b110 ^
1#
#1360000
0#
#1365000
b11000 d
1B
0-
1.
b100 1
b1000 2
b0 ^
1#
#1370000
b1 !
b1 3
b100000 5
b11000 "
b11000 )
1&
0#
#1371000
b10000 d
#1375000
1:
b100000 ;
b100000 O
b100000 P
b0 +
b0 >
b0 V
b11111111111111111111111111110100 ?
b11111111111111111111111111110100 R
b11111111111111111111111111110100 _
b0 ,
b0 8
b0 9
b0 S
b0 a
b1100100 G
b1100100 K
1#
#1380000
b1000 !
b1000 3
b1000 5
b10000 "
b10000 )
0#
#1381000
b10100 d
#1385000
1#
#1390000
b100 !
b100 3
b10000 5
b10100 "
b10100 )
0#
#1391000
b11001 b
b100 c
#1395000
1#
#1400000
b1 5
b0 !
b0 3
b11001 %
b11001 *
b100 "
b100 )
0&
1(
0#
#1405000
b11001 0
b11001 7
b11001 I
1#
#1410000
b101 b
b1000 c
0(
0#
#1415000
b11001 G
b11001 K
1#
#1420000
b10 5
b101 %
b101 *
b1000 "
b1000 )
1(
0#
#1425000
b101 /
b101 6
b101 L
1#
#1430000
b1 b
b1100 c
0(
0#
#1435000
b11111111111111111111111111111011 ?
b11111111111111111111111111111011 R
b11111111111111111111111111111011 _
b101 F
b101 N
b101 Q
1#
#1440000
b100 5
b1 %
b1 *
b1100 "
b1100 )
1(
0#
#1445000
b0 1
b0 2
0.
14
1#
#1450000
0(
0#
#1451000
b0 b
#1455000
1E
1=
0B
b1 ^
1#
#1460000
b0 %
b0 *
1(
0#
#1465000
0E
0=
b110010 G
b110010 K
b11111 ;
b11111 O
b11111 P
04
b10 ^
1#
#1470000
0(
0#
#1475000
1D
b11 ^
1#
#1480000
0#
#1485000
0D
b101 ^
1#
#1490000
0#
#1495000
1E
1=
b1 ^
1#
#1500000
0#
#1505000
0E
0=
b1100100 G
b1100100 K
b11110 ;
b11110 O
b11110 P
b10 ^
1#
#1510000
0#
#1515000
1D
b11 ^
1#
#1520000
0#
#1525000
0D
b101 ^
1#
#1530000
0#
#1535000
1E
1=
b1 ^
1#
#1540000
0#
#1545000
0E
0=
b11001000 G
b11001000 K
b11101 ;
b11101 O
b11101 P
b10 ^
1#
#1550000
0#
#1555000
1D
b11 ^
1#
#1560000
0#
#1565000
0D
b101 ^
1#
#1570000
0#
#1575000
1E
1=
b1 ^
1#
#1580000
0#
#1585000
0E
0=
b110010000 G
b110010000 K
b11100 ;
b11100 O
b11100 P
b10 ^
1#
