rtl/Cores/BCD a Binario/Control_BCDbinario.v
module Control_BCDbinario (
    input clk,
    input reset,
    input init,
    input M,
    input C,
    output reg LD,
    output reg SH,
    output reg SUB3,
    output reg DEC,
    output reg DONE
);

    parameter START       = 3'b000;
    parameter SHIFT       = 3'b001;
    parameter CHECK_BCD   = 3'b010;
    parameter SUB3_STATE  = 3'b011;
    parameter DEC_COUNT   = 3'b100;
    parameter CHECK_COUNT = 3'b101;
    parameter END_STATE   = 3'b110;

    reg [2:0] state;

    always @(posedge clk) begin
        if (reset) begin
            state <= START;
        end
        else begin
            case (state)
                START: begin
                    if (init)
                        state <= SHIFT;
                    else
                        state <= START;
                end

                SHIFT: begin
                    state <= CHECK_BCD;
                end

                CHECK_BCD: begin
                    if (M)
                        state <= SUB3_STATE;
                    else
                        state <= DEC_COUNT;
                end

                SUB3_STATE: begin
                    state <= DEC_COUNT;
                end

                DEC_COUNT: begin
                    state <= CHECK_COUNT;
                end

                CHECK_COUNT: begin
                    if (C)
                        state <= SHIFT;
                    else
                        state <= END_STATE;
                end

                END_STATE: begin
                    state <= START;
                end

                default: begin
                    state <= START;
                end
            endcase
        end
    end

    always @(*) begin
        LD   = 0;
        SH   = 0;
        SUB3 = 0;
        DEC  = 0;
        DONE = 0;

        case (state)
            START: begin
                LD   = 1;
            end

            SHIFT: begin
                SH   = 1;
            end

            CHECK_BCD: begin
                // Solo revisa M
            end

            SUB3_STATE: begin
                SUB3 = 1;
            end

            DEC_COUNT: begin
                DEC = 1;
            end

            CHECK_COUNT: begin
                // Solo revisa C
            end

            END_STATE: begin
                DONE = 1;
            end
        endcase
    end

endmodule

Calculadora/rtl/Cores/BCD_Binario/Comp_count_BCDbinario.v
module Comp_count_BCDbinario (
    input [5:0] count,
    output C
);

    assign C = (count != 6'd0);

endmodule

Calculadora/rtl/Cores/BCD_Binario/Count_BCDbinario.v
module Count_BCDbinario (
    input clk,
    input LD,
    input DEC,
    output reg [5:0] count
);

    always @(posedge clk) begin
        if (LD) begin
            count <= 6'd32;
        end
        else if (DEC) begin
            count <= count - 1'b1;
        end
        else begin
            count <= count;
        end
    end

endmodule

Calculadora/rtl/Cores/BCD_Binario/Comparador_BCDbinario.v
module Comparador_BCDbinario (
    input [31:0] BCD_in,
    output [7:0] M_digit,
    output M
);

    assign M_digit[0] = (BCD_in[3:0]   >= 4'd8);
    assign M_digit[1] = (BCD_in[7:4]   >= 4'd8);
    assign M_digit[2] = (BCD_in[11:8]  >= 4'd8);
    assign M_digit[3] = (BCD_in[15:12] >= 4'd8);
    assign M_digit[4] = (BCD_in[19:16] >= 4'd8);
    assign M_digit[5] = (BCD_in[23:20] >= 4'd8);
    assign M_digit[6] = (BCD_in[27:24] >= 4'd8);
    assign M_digit[7] = (BCD_in[31:28] >= 4'd8);

    assign M = |M_digit;

endmodule

rtl/Cores/BCD a Binario/Binario_BCDbinario.v
module Binario_BCDbinario (
    input clk,
    input LD,
    input SH,
    input LSB_BCD,
    output reg [31:0] BIN_out
);

    always @(posedge clk) begin
        if (LD) begin
            BIN_out <= 32'd0;
        end
        else if (SH) begin
            BIN_out <= {LSB_BCD, BIN_out[31:1]};
        end
        else begin
            BIN_out <= BIN_out;
        end
    end

endmodule

Calculadora/rtl/Cores/BCD_Binario/BCD_process_BCDbinario.v
module BCD_process_BCDbinario (
    input clk,
    input LD,
    input SH,
    input SUB3,
    input [31:0] BCD,
    input [7:0] M_digit,
    output reg [31:0] BCD_out,
    output LSB_BCD
);

    assign LSB_BCD = BCD_out[0];

    always @(posedge clk) begin
        if (LD) begin
            BCD_out <= BCD;
        end
        else if (SH) begin
            BCD_out <= {1'b0, BCD_out[31:1]};
        end
        else if (SUB3) begin
            BCD_out[3:0]   <= M_digit[0] ? BCD_out[3:0]   - 4'd3 : BCD_out[3:0];
            BCD_out[7:4]   <= M_digit[1] ? BCD_out[7:4]   - 4'd3 : BCD_out[7:4];
            BCD_out[11:8]  <= M_digit[2] ? BCD_out[11:8]  - 4'd3 : BCD_out[11:8];
            BCD_out[15:12] <= M_digit[3] ? BCD_out[15:12] - 4'd3 : BCD_out[15:12];
            BCD_out[19:16] <= M_digit[4] ? BCD_out[19:16] - 4'd3 : BCD_out[19:16];
            BCD_out[23:20] <= M_digit[5] ? BCD_out[23:20] - 4'd3 : BCD_out[23:20];
            BCD_out[27:24] <= M_digit[6] ? BCD_out[27:24] - 4'd3 : BCD_out[27:24];
            BCD_out[31:28] <= M_digit[7] ? BCD_out[31:28] - 4'd3 : BCD_out[31:28];
        end
        else begin
            BCD_out <= BCD_out;
        end
    end

endmodule

rtl/Cores/BCD a Binario/TOP_BCDbinario.v
module TOP_BCDbinario (
    input clk,
    input reset,
    input init,
    input [31:0] BCD,
    output [31:0] BIN,
    output DONE
);

    wire LD;
    wire SH;
    wire SUB3;
    wire DEC;

    wire [31:0] BCD_out;
    wire LSB_BCD;

    wire [31:0] BIN_out;

    wire [7:0] M_digit;
    wire M;

    wire [5:0] count;
    wire C;

    BCD_process_BCDbinario U1 (
        .clk(clk),
        .LD(LD),
        .SH(SH),
        .SUB3(SUB3),
        .BCD(BCD),
        .BCD_out(BCD_out),
        .LSB_BCD(LSB_BCD),
        .M_digit(M_digit)
    );

    Binario_BCDbinario U2 (
        .clk(clk),
        .LD(LD),
        .SH(SH),
        .LSB_BCD(LSB_BCD),
        .BIN_out(BIN_out)
    );

    Comparador_BCDbinario U3 (
        .BCD_in(BCD_out),
        .M_digit(M_digit),
        .M(M)
    );

    Count_BCDbinario U4 (
        .clk(clk),
        .LD(LD),
        .DEC(DEC),
        .count(count)
    );

    Comp_count_BCDbinario U5 (
        .count(count),
        .C(C)
    );

    Control_BCDbinario U6 (
        .clk(clk),
        .reset(reset),
        .init(init),
        .M(M),
        .C(C),
        .LD(LD),
        .SH(SH),
        .SUB3(SUB3),
        .DEC(DEC),
        .DONE(DONE)
    );

    assign BIN = BIN_out;

endmodule

rtl/Cores/BCD a Binario/Periferico_BCDbinario.v
module Periferico_BCDbinario (
    input clk,
    input reset,

    input [31:0] d_in,
    input cs,
    input [4:0] addr,
    input rd,
    input wr,

    output reg [31:0] d_out
);

    reg [3:0] s;

    reg [31:0] BCD_reg;
    reg init;

    wire [31:0] BIN_wire;
    wire DONE_wire;

    reg [31:0] BIN_reg;
    reg DONE_reg;

    always @(*) begin
        if (cs) begin
            case (addr)
                5'h04: s = 4'b0001; // BCD entrada
                5'h08: s = 4'b0010; // init
                5'h0C: s = 4'b0100; // Resultado BIN
                5'h10: s = 4'b1000; // DONE
                default: s = 4'b0000;
            endcase
        end
        else begin
            s = 4'b0000;
        end
    end

    always @(posedge clk) begin
        if (reset) begin
            BCD_reg  <= 32'b0;
            init     <= 1'b0;
            BIN_reg  <= 32'b0;
            DONE_reg <= 1'b0;
        end
        else begin

            if (cs && wr) begin
                if (s[0])
                    BCD_reg <= d_in;

                if (s[1]) begin
                    init <= d_in[0];

                    if (d_in[0] == 1'b1) begin
                        DONE_reg <= 1'b0;
                        BIN_reg  <= 32'b0;
                    end
                end
            end

            if (DONE_wire) begin
                BIN_reg  <= BIN_wire;
                DONE_reg <= 1'b1;
            end

        end
    end

    always @(posedge clk) begin
        if (reset) begin
            d_out <= 32'b0;
        end
        else if (cs && rd) begin
            case (addr)
                5'h0C: d_out <= BIN_reg;
                5'h10: d_out <= {31'b0, DONE_reg};
                default: d_out <= 32'b0;
            endcase
        end
    end

    TOP_BCDbinario U_TOP_BCDBIN (
        .clk(clk),
        .reset(reset),
        .init(init),
        .BCD(BCD_reg),
        .BIN(BIN_wire),
        .DONE(DONE_wire)
    );

endmodule

rtl/Cores/BCD a Binario/Testbench_Periferico_BCDbinario.v
`timescale 1ns / 1ps

module Testbench_Periferico_BCDbinario;

    reg clk;
    reg reset;
    reg cs;
    reg rd;
    reg wr;
    reg [4:0] addr;
    reg [31:0] d_in;

    wire [31:0] d_out;

    Periferico_BCDbinario uut (
        .clk(clk),
        .reset(reset),
        .d_in(d_in),
        .cs(cs),
        .addr(addr),
        .rd(rd),
        .wr(wr),
        .d_out(d_out)
    );

    always #10 clk = ~clk;

    task write_reg;
        input [4:0] address;
        input [31:0] data;
        begin
            @(posedge clk);
            cs   = 1;
            wr   = 1;
            rd   = 0;
            addr = address;
            d_in = data;

            @(posedge clk);
            cs   = 0;
            wr   = 0;
            addr = 5'h00;
            d_in = 32'h00000000;
        end
    endtask

    task read_reg;
        input [4:0] address;
        output [31:0] data;
        begin
            @(posedge clk);
            cs   = 1;
            rd   = 1;
            wr   = 0;
            addr = address;

            #1;
            data = d_out;

            @(posedge clk);
            cs   = 0;
            rd   = 0;
            addr = 5'h00;
        end
    endtask

    task run_test;
        input [31:0] entrada_bcd;
        input [31:0] esperado_bin;

        reg [31:0] done_read;
        reg [31:0] result_read;
        integer timeout;

        begin
            $display("----------------------------------");
            $display("PERIFERICO BCD A BINARIO");
            $display("Entrada BCD h    = %h", entrada_bcd);

            write_reg(5'h04, entrada_bcd);

            write_reg(5'h08, 32'h00000001);
            write_reg(5'h08, 32'h00000000);

            done_read = 32'h00000000;
            timeout = 0;

            while (done_read[0] == 1'b0 && timeout < 200) begin
                read_reg(5'h10, done_read);
                timeout = timeout + 1;
            end

            read_reg(5'h0C, result_read);

            $display("DONE leído       = %h", done_read);
            $display("Resultado dec    = %0d", result_read);
            $display("Resultado hex    = %h", result_read);
            $display("Esperado dec     = %0d", esperado_bin);

            if (result_read == esperado_bin && done_read[0] == 1'b1)
                $display("PRUEBA PERIFERICO OK");
            else
                $display("PRUEBA PERIFERICO ERROR");

            // Verificación: DONE_reg debe quedarse en 1
            repeat (5) @(posedge clk);
            read_reg(5'h10, done_read);

            if (done_read[0] == 1'b1)
                $display("DONE_reg se mantiene OK");
            else
                $display("ERROR: DONE_reg no se mantuvo");

            @(posedge clk);
        end
    endtask

    initial begin
        $dumpfile("Testbench_Periferico_BCDbinario.vcd");
        $dumpvars(0, Testbench_Periferico_BCDbinario);

        clk = 0;
        reset = 1;
        cs = 0;
        rd = 0;
        wr = 0;
        addr = 5'h00;
        d_in = 32'h00000000;

        #50;
        reset = 0;

        
        run_test(32'h00000123, 32'd123);
        

        #100;
        $finish;
    end

endmodule

// iverilog -s Testbench_Periferico_BCDbinario -o sim *.v
// vvp sim
// gtkwave Testbench_Periferico_BCDbinario.vcd

rtl/Cores/BCD a Binario/Testbench_Periferico_BCDbinario.vcd
$date
	Tue Jun  9 11:05:01 2026
$end
$version
	Icarus Verilog
$end
$timescale
	1ps
$end
$scope module Testbench_Periferico_BCDbinario $end
$var wire 32 ! d_out [31:0] $end
$var reg 5 " addr [4:0] $end
$var reg 1 # clk $end
$var reg 1 $ cs $end
$var reg 32 % d_in [31:0] $end
$var reg 1 & rd $end
$var reg 1 ' reset $end
$var reg 1 ( wr $end
$scope module uut $end
$var wire 5 ) addr [4:0] $end
$var wire 1 # clk $end
$var wire 1 $ cs $end
$var wire 32 * d_in [31:0] $end
$var wire 1 & rd $end
$var wire 1 ' reset $end
$var wire 1 ( wr $end
$var wire 1 + DONE_wire $end
$var wire 32 , BIN_wire [31:0] $end
$var reg 32 - BCD_reg [31:0] $end
$var reg 32 . BIN_reg [31:0] $end
$var reg 1 / DONE_reg $end
$var reg 32 0 d_out [31:0] $end
$var reg 1 1 init $end
$var reg 4 2 s [3:0] $end
$scope module U_TOP_BCDBIN $end
$var wire 32 3 BCD [31:0] $end
$var wire 32 4 BIN [31:0] $end
$var wire 1 # clk $end
$var wire 1 1 init $end
$var wire 1 ' reset $end
$var wire 6 5 count [5:0] $end
$var wire 1 6 SUB3 $end
$var wire 1 7 SH $end
$var wire 8 8 M_digit [7:0] $end
$var wire 1 9 M $end
$var wire 1 : LSB_BCD $end
$var wire 1 ; LD $end
$var wire 1 + DONE $end
$var wire 1 < DEC $end
$var wire 1 = C $end
$var wire 32 > BIN_out [31:0] $end
$var wire 32 ? BCD_out [31:0] $end
$scope module U1 $end
$var wire 32 @ BCD [31:0] $end
$var wire 1 # clk $end
$var wire 1 6 SUB3 $end
$var wire 1 7 SH $end
$var wire 8 A M_digit [7:0] $end
$var wire 1 : LSB_BCD $end
$var wire 1 ; LD $end
$var reg 32 B BCD_out [31:0] $end
$upscope $end
$scope module U2 $end
$var wire 1 : LSB_BCD $end
$var wire 1 # clk $end
$var wire 1 7 SH $end
$var wire 1 ; LD $end
$var reg 32 C BIN_out [31:0] $end
$upscope $end
$scope module U3 $end
$var wire 32 D BCD_in [31:0] $end
$var wire 8 E M_digit [7:0] $end
$var wire 1 9 M $end
$upscope $end
$scope module U4 $end
$var wire 1 # clk $end
$var wire 1 ; LD $end
$var wire 1 < DEC $end
$var reg 6 F count [5:0] $end
$upscope $end
$scope module U5 $end
$var wire 6 G count [5:0] $end
$var wire 1 = C $end
$upscope $end
$scope module U6 $end
$var wire 1 = C $end
$var wire 1 9 M $end
$var wire 1 # clk $end
$var wire 1 1 init $end
$var wire 1 ' reset $end
$var parameter 3 H CHECK_BCD $end
$var parameter 3 I CHECK_COUNT $end
$var parameter 3 J DEC_COUNT $end
$var parameter 3 K END_STATE $end
$var parameter 3 L SHIFT $end
$var parameter 3 M START $end
$var parameter 3 N SUB3_STATE $end
$var reg 1 < DEC $end
$var reg 1 + DONE $end
$var reg 1 ; LD $end
$var reg 1 7 SH $end
$var reg 1 6 SUB3 $end
$var reg 3 O state [2:0] $end
$upscope $end
$upscope $end
$upscope $end
$scope task read_reg $end
$var reg 5 P address [4:0] $end
$var reg 32 Q data [31:0] $end
$upscope $end
$scope task run_test $end
$var reg 32 R done_read [31:0] $end
$var reg 32 S entrada_bcd [31:0] $end
$var reg 32 T esperado_bin [31:0] $end
$var reg 32 U result_read [31:0] $end
$var integer 32 V timeout [31:0] $end
$upscope $end
$scope task write_reg $end
$var reg 5 W address [4:0] $end
$var reg 32 X data [31:0] $end
$upscope $end
$upscope $end
$enddefinitions $end
$comment Show the parameter values. $end
$dumpall
b11 N
b0 M
b1 L
b110 K
b100 J
b101 I
b10 H
$end
#0
$dumpvars
bx X
bx W
bx V
bx U
bx T
bx S
bx R
bx Q
bx P
bx O
bx G
bx F
bx E
bx D
bx C
bx B
bx A
bx @
bx ?
bx >
x=
x<
x;
x:
x9
bx 8
x7
x6
bx 5
bx 4
bx 3
b0 2
x1
bx 0
x/
bx .
bx -
bx ,
x+
b0 *
b0 )
0(
1'
0&
b0 %
0$
0#
b0 "
bx !
$end
#10000
0+
0<
06
07
1;
b0 O
0/
b0 .
01
b0 -
b0 3
b0 @
b0 !
b0 0
1#
#20000
0#
#30000
0:
09
b0 8
b0 A
b0 E
1=
b100000 5
b100000 F
b100000 G
b0 ,
b0 4
b0 >
b0 C
b0 ?
b0 B
b0 D
1#
#40000
0#
#50000
1#
b100100011 X
b100 W
b1111011 T
b100100011 S
0'
#60000
b1 2
b100100011 %
b100100011 *
b100 "
b100 )
1(
1$
0#
#70000
b100100011 -
b100100011 3
b100100011 @
1#
#80000
b0 2
b1 X
b1000 W
b0 %
b0 *
b0 "
b0 )
0(
0$
0#
#90000
1:
b100100011 ?
b100100011 B
b100100011 D
1#
#100000
b10 2
b1 %
b1 *
b1000 "
b1000 )
1(
1$
0#
#110000
11
1#
#120000
b0 2
b0 X
b0 %
b0 *
b0 "
b0 )
0(
0$
0#
#130000
17
0;
b1 O
1#
#140000
b10 2
b1000 "
b1000 )
1(
1$
0#
#150000
07
19
b10 8
b10 A
b10 E
01
b10 O
b10000000000000000000000000000000 ,
b10000000000000000000000000000000 4
b10000000000000000000000000000000 >
b10000000000000000000000000000000 C
b10010001 ?
b10010001 B
b10010001 D
1#
#160000
b0 2
b10000 P
b0 V
b0 R
b0 "
b0 )
0(
0$
0#
#170000
16
b11 O
1#
#180000
b1000 2
b10000 "
b10000 )
1&
1$
0#
#190000
1<
06
09
b0 8
b0 A
b0 E
b100 O
b1100001 ?
b1100001 B
b1100001 D
1#
#191000
b0 Q
#200000
b0 2
b1 V
b0 "
b0 )
0&
0$
0#
#210000
0<
b11111 5
b11111 F
b11111 G
b101 O
1#
#220000
b1000 2
b10000 "
b10000 )
1&
1$
0#
#230000
17
b1 O
1#
#240000
b0 2
b10 V
b0 "
b0 )
0&
0$
0#
#250000
0:
07
b110000 ?
b110000 B
b110000 D
b11000000000000000000000000000000 ,
b11000000000000000000000000000000 4
b11000000000000000000000000000000 >
b11000000000000000000000000000000 C
b10 O
1#
#260000
b1000 2
b10000 "
b10000 )
1&
1$
0#
#270000
1<
b100 O
1#
#280000
b0 2
b11 V
b0 "
b0 )
0&
0$
0#
#290000
0<
b11110 5
b11110 F
b11110 G
b101 O
1#
#300000
b1000 2
b10000 "
b10000 )
1&
1$
0#
#310000
17
b1 O
1#
#320000
b0 2
b100 V
b0 "
b0 )
0&
0$
0#
#330000
19
b1 8
b1 A
b1 E
07
b11000 ?
b11000 B
b11000 D
b1100000000000000000000000000000 ,
b1100000000000000000000000000000 4
b1100000000000000000000000000000 >
b1100000000000000000000000000000 C
b10 O
1#
#340000
b1000 2
b10000 "
b10000 )
1&
1$
0#
#350000
16
b11 O
1#
#360000
b0 2
b101 V
b0 "
b0 )
0&
0$
0#
#370000
1:
09
b0 8
b0 A
b0 E
1<
06
b10101 ?
b10101 B
b10101 D
b100 O
1#
#380000
b1000 2
b10000 "
b10000 )
1&
1$
0#
#390000
0<
b101 O
b11101 5
b11101 F
b11101 G
1#
#400000
b0 2
b110 V
b0 "
b0 )
0&
0$
0#
#410000
17
b1 O
1#
#420000
b1000 2
b10000 "
b10000 )
1&
1$
0#
#430000
07
0:
19
b1 8
b1 A
b1 E
b10 O
b10110000000000000000000000000000 ,
b10110000000000000000000000000000 4
b10110000000000000000000000000000 >
b10110000000000000000000000000000 C
b1010 ?
b1010 B
b1010 D
1#
#440000
b0 2
b111 V
b0 "
b0 )
0&
0$
0#
#450000
16
b11 O
1#
#460000
b1000 2
b10000 "
b10000 )
1&
1$
0#
#470000
1<
06
1:
09
b0 8
b0 A
b0 E
b100 O
b111 ?
b111 B
b111 D
1#
#480000
b0 2
b1000 V
b0 "
b0 )
0&
0$
0#
#490000
0<
b11100 5
b11100 F
b11100 G
b101 O
1#
#500000
b1000 2
b10000 "
b10000 )
1&
1$
0#
#510000
17
b1 O
1#
#520000
b0 2
b1001 V
b0 "
b0 )
0&
0$
0#
#530000
07
b11 ?
b11 B
b11 D
b11011000000000000000000000000000 ,
b11011000000000000000000000000000 4
b11011000000000000000000000000000 >
b11011000000000000000000000000000 C
b10 O
1#
#540000
b1000 2
b10000 "
b10000 )
1&
1$
0#
#550000
1<
b100 O
1#
#560000
b0 2
b1010 V
b0 "
b0 )
0&
0$
0#
#570000
0<
b11011 5
b11011 F
b11011 G
b101 O
1#
#580000
b1000 2
b10000 "
b10000 )
1&
1$
0#
#590000
17
b1 O
1#
#600000
b0 2
b1011 V
b0 "
b0 )
0&
0$
0#
#610000
07
b1 ?
b1 B
b1 D
b11101100000000000000000000000000 ,
b11101100000000000000000000000000 4
b11101100000000000000000000000000 >
b11101100000000000000000000000000 C
b10 O
1#
#620000
b1000 2
b10000 "
b10000 )
1&
1$
0#
#630000
1<
b100 O
1#
#640000
b0 2
b1100 V
b0 "
b0 )
0&
0$
0#
#650000
0<
b11010 5
b11010 F
b11010 G
b101 O
1#
#660000
b1000 2
b10000 "
b10000 )
1&
1$
0#
#670000
17
b1 O
1#
#680000
b0 2
b1101 V
b0 "
b0 )
0&
0$
0#
#690000
0:
07
b0 ?
b0 B
b0 D
b11110110000000000000000000000000 ,
b11110110000000000000000000000000 4
b11110110000000000000000000000000 >
b11110110000000000000000000000000 C
b10 O
1#
#700000
b1000 2
b10000 "
b10000 )
1&
1$
0#
#710000
1<
b100 O
1#
#720000
b0 2
b1110 V
b0 "
b0 )
0&
0$
0#
#730000
0<
b11001 5
b11001 F
b11001 G
b101 O
1#
#740000
b1000 2
b10000 "
b10000 )
1&
1$
0#
#750000
17
b1 O
1#
#760000
b0 2
b1111 V
b0 "
b0 )
0&
0$
0#
#770000
07
b1111011000000000000000000000000 ,
b1111011000000000000000000000000 4
b1111011000000000000000000000000 >
b1111011000000000000000000000000 C
b10 O
1#
#780000
b1000 2
b10000 "
b10000 )
1&
1$
0#
#790000
1<
b100 O
1#
#800000
b0 2
b10000 V
b0 "
b0 )
0&
0$
0#
#810000
0<
b11000 5
b11000 F
b11000 G
b101 O
1#
#820000
b1000 2
b10000 "
b10000 )
1&
1$
0#
#830000
17
b1 O
1#
#840000
b0 2
b10001 V
b0 "
b0 )
0&
0$
0#
#850000
07
b111101100000000000000000000000 ,
b111101100000000000000000000000 4
b111101100000000000000000000000 >
b111101100000000000000000000000 C
b10 O
1#
#860000
b1000 2
b10000 "
b10000 )
1&
1$
0#
#870000
1<
b100 O
1#
#880000
b0 2
b10010 V
b0 "
b0 )
0&
0$
0#
#890000
0<
b10111 5
b10111 F
b10111 G
b101 O
1#
#900000
b1000 2
b10000 "
b10000 )
1&
1$
0#
#910000
17
b1 O
1#
#920000
b0 2
b10011 V
b0 "
b0 )
0&
0$
0#
#930000
07
b11110110000000000000000000000 ,
b11110110000000000000000000000 4
b11110110000000000000000000000 >
b11110110000000000000000000000 C
b10 O
1#
#940000
b1000 2
b10000 "
b10000 )
1&
1$
0#
#950000
1<
b100 O
1#
#960000
b0 2
b10100 V
b0 "
b0 )
0&
0$
0#
#970000
0<
b10110 5
b10110 F
b10110 G
b101 O
1#
#980000
b1000 2
b10000 "
b10000 )
1&
1$
0#
#990000
17
b1 O
1#
#1000000
b0 2
b10101 V
b0 "
b0 )
0&
0$
0#
#1010000
07
b1111011000000000000000000000 ,
b1111011000000000000000000000 4
b1111011000000000000000000000 >
b1111011000000000000000000000 C
b10 O
1#
#1020000
b1000 2
b10000 "
b10000 )
1&
1$
0#
#1030000
1<
b100 O
1#
#1040000
b0 2
b10110 V
b0 "
b0 )
0&
0$
0#
#1050000
0<
b10101 5
b10101 F
b10101 G
b101 O
1#
#1060000
b1000 2
b10000 "
b10000 )
1&
1$
0#
#1070000
17
b1 O
1#
#1080000
b0 2
b10111 V
b0 "
b0 )
0&
0$
0#
#1090000
07
b111101100000000000000000000 ,
b111101100000000000000000000 4
b111101100000000000000000000 >
b111101100000000000000000000 C
b10 O
1#
#1100000
b1000 2
b10000 "
b10000 )
1&
1$
0#
#1110000
1<
b100 O
1#
#1120000
b0 2
b11000 V
b0 "
b0 )
0&
0$
0#
#1130000
0<
b10100 5
b10100 F
b10100 G
b101 O
1#
#1140000
b1000 2
b10000 "
b10000 )
1&
1$
0#
#1150000
17
b1 O
1#
#1160000
b0 2
b11001 V
b0 "
b0 )
0&
0$
0#
#1170000
07
b11110110000000000000000000 ,
b11110110000000000000000000 4
b11110110000000000000000000 >
b11110110000000000000000000 C
b10 O
1#
#1180000
b1000 2
b10000 "
b10000 )
1&
1$
0#
#1190000
1<
b100 O
1#
#1200000
b0 2
b11010 V
b0 "
b0 )
0&
0$
0#
#1210000
0<
b10011 5
b10011 F
b10011 G
b101 O
1#
#1220000
b1000 2
b10000 "
b10000 )
1&
1$
0#
#1230000
17
b1 O
1#
#1240000
b0 2
b11011 V
b0 "
b0 )
0&
0$
0#
#1250000
07
b1111011000000000000000000 ,
b1111011000000000000000000 4
b1111011000000000000000000 >
b1111011000000000000000000 C
b10 O
1#
#1260000
b1000 2
b10000 "
b10000 )
1&
1$
0#
#1270000
1<
b100 O
1#
#1280000
b0 2
b11100 V
b0 "
b0 )
0&
0$
0#
#1290000
0<
b10010 5
b10010 F
b10010 G
b101 O
1#
#1300000
b1000 2
b10000 "
b10000 )
1&
1$
0#
#1310000
17
b1 O
1#
#1320000
b0 2
b11101 V
b0 "
b0 )
0&
0$
0#
#1330000
07
b111101100000000000000000 ,
b111101100000000000000000 4
b111101100000000000000000 >
b111101100000000000000000 C
b10 O
1#
#1340000
b1000 2
b10000 "
b10000 )
1&
1$
0#
#1350000
1<
b100 O
1#
#1360000
b0 2
b11110 V
b0 "
b0 )
0&
0$
0#
#1370000
0<
b10001 5
b10001 F
b10001 G
b101 O
1#
#1380000
b1000 2
b10000 "
b10000 )
1&
1$
0#
#1390000
17
b1 O
1#
#1400000
b0 2
b11111 V
b0 "
b0 )
0&
0$
0#
#1410000
07
b11110110000000000000000 ,
b11110110000000000000000 4
b11110110000000000000000 >
b11110110000000000000000 C
b10 O
1#
#1420000
b1000 2
b10000 "
b10000 )
1&
1$
0#
#1430000
1<
b100 O
1#
#1440000
b0 2
b100000 V
b0 "
b0 )
0&
0$
0#
#1450000
0<
b10000 5
b10000 F
b10000 G
b101 O
1#
#1460000
b1000 2
b10000 "
b10000 )
1&
1$
0#
#1470000
17
b1 O
1#
#1480000
b0 2
b100001 V
b0 "
b0 )
0&
0$
0#
#1490000
07
b1111011000000000000000 ,
b1111011000000000000000 4
b1111011000000000000000 >
b1111011000000000000000 C
b10 O
1#
#1500000
b1000 2
b10000 "
b10000 )
1&
1$
0#
#1510000
1<
b100 O
1#
#1520000
b0 2
b100010 V
b0 "
b0 )
0&
0$
0#
#1530000
0<
b1111 5
b1111 F
b1111 G
b101 O
1#
#1540000
b1000 2
b10000 "
b10000 )
1&
1$
0#
#1550000
17
b1 O
1#
#1560000
b0 2
b100011 V
b0 "
b0 )
0&
0$
0#
#1570000
07
b111101100000000000000 ,
b111101100000000000000 4
b111101100000000000000 >
b111101100000000000000 C
b10 O
1#
#1580000
b1000 2
b10000 "
b10000 )
1&
1$
0#
#1590000
1<
b100 O
1#
#1600000
b0 2
b100100 V
b0 "
b0 )
0&
0$
0#
#1610000
0<
b1110 5
b1110 F
b1110 G
b101 O
1#
#1620000
b1000 2
b10000 "
b10000 )
1&
1$
0#
#1630000
17
b1 O
1#
#1640000
b0 2
b100101 V
b0 "
b0 )
0&
0$
0#
#1650000
07
b11110110000000000000 ,
b11110110000000000000 4
b11110110000000000000 >
b11110110000000000000 C
b10 O
1#
#1660000
b1000 2
b10000 "
b10000 )
1&
1$
0#
#1670000
1<
b100 O
1#
#1680000
b0 2
b100110 V
b0 "
b0 )
0&
0$
0#
#1690000
0<
b1101 5
b1101 F
b1101 G
b101 O
1#
#1700000
b1000 2
b10000 "
b10000 )
1&
1$
0#
#1710000
17
b1 O
1#
#1720000
b0 2
b100111 V
b0 "
b0 )
0&
0$
0#
#1730000
07
b1111011000000000000 ,
b1111011000000000000 4
b1111011000000000000 >
b1111011000000000000 C
b10 O
1#
#1740000
b1000 2
b10000 "
b10000 )
1&
1$
0#
#1750000
1<
b100 O
1#
#1760000
b0 2
b101000 V
b0 "
b0 )
0&
0$
0#
#1770000
0<
b1100 5
b1100 F
b1100 G
b101 O
1#
#1780000
b1000 2
b10000 "
b10000 )
1&
1$
0#
#1790000
17
b1 O
1#
#1800000
b0 2
b101001 V
b0 "
b0 )
0&
0$
0#
#1810000
07
b111101100000000000 ,
b111101100000000000 4
b111101100000000000 >
b111101100000000000 C
b10 O
1#
#1820000
b1000 2
b10000 "
b10000 )
1&
1$
0#
#1830000
1<
b100 O
1#
#1840000
b0 2
b101010 V
b0 "
b0 )
0&
0$
0#
#1850000
0<
b1011 5
b1011 F
b1011 G
b101 O
1#
#1860000
b1000 2
b10000 "
b10000 )
1&
1$
0#
#1870000
17
b1 O
1#
#1880000
b0 2
b101011 V
b0 "
b0 )
0&
0$
0#
#1890000
07
b11110110000000000 ,
b11110110000000000 4
b11110110000000000 >
b11110110000000000 C
b10 O
1#
#1900000
b1000 2
b10000 "
b10000 )
1&
1$
0#
#1910000
1<
b100 O
1#
#1920000
b0 2
b101100 V
b0 "
b0 )
0&
0$
0#
#1930000
0<
b1010 5
b1010 F
b1010 G
b101 O
1#
#1940000
b1000 2
b10000 "
b10000 )
1&
1$
0#
#1950000
17
b1 O
1#
#1960000
b0 2
b101101 V
b0 "
b0 )
0&
0$
0#
#1970000
07
b1111011000000000 ,
b1111011000000000 4
b1111011000000000 >
b1111011000000000 C
b10 O
1#
#1980000
b1000 2
b10000 "
b10000 )
1&
1$
0#
#1990000
1<
b100 O
1#
#2000000
b0 2
b101110 V
b0 "
b0 )
0&
0$
0#
#2010000
0<
b1001 5
b1001 F
b1001 G
b101 O
1#
#2020000
b1000 2
b10000 "
b10000 )
1&
1$
0#
#2030000
17
b1 O
1#
#2040000
b0 2
b101111 V
b0 "
b0 )
0&
0$
0#
#2050000
07
b111101100000000 ,
b111101100000000 4
b111101100000000 >
b111101100000000 C
b10 O
1#
#2060000
b1000 2
b10000 "
b10000 )
1&
1$
0#
#2070000
1<
b100 O
1#
#2080000
b0 2
b110000 V
b0 "
b0 )
0&
0$
0#
#2090000
0<
b1000 5
b1000 F
b1000 G
b101 O
1#
#2100000
b1000 2
b10000 "
b10000 )
1&
1$
0#
#2110000
17
b1 O
1#
#2120000
b0 2
b110001 V
b0 "
b0 )
0&
0$
0#
#2130000
07
b11110110000000 ,
b11110110000000 4
b11110110000000 >
b11110110000000 C
b10 O
1#
#2140000
b1000 2
b10000 "
b10000 )
1&
1$
0#
#2150000
1<
b100 O
1#
#2160000
b0 2
b110010 V
b0 "
b0 )
0&
0$
0#
#2170000
0<
b111 5
b111 F
b111 G
b101 O
1#
#2180000
b1000 2
b10000 "
b10000 )
1&
1$
0#
#2190000
17
b1 O
1#
#2200000
b0 2
b110011 V
b0 "
b0 )
0&
0$
0#
#2210000
07
b1111011000000 ,
b1111011000000 4
b1111011000000 >
b1111011000000 C
b10 O
1#
#2220000
b1000 2
b10000 "
b10000 )
1&
1$
0#
#2230000
1<
b100 O
1#
#2240000
b0 2
b110100 V
b0 "
b0 )
0&
0$
0#
#2250000
0<
b110 5
b110 F
b110 G
b101 O
1#
#2260000
b1000 2
b10000 "
b10000 )
1&
1$
0#
