Calculadora/rtl/Cores/Multiplicador/Control_Multiplicador.v
module Control_Multiplicador (

    input clk,
    input reset,
    input init,
    input C,
    input LSB_B_process,

    output reg ADD_EN,
    output reg SH,
    output reg DEC,
    output reg LD,
    output reg DONE

);

// DEFINICIÓN DE ESTADOS

    parameter S_START = 3'b000;
    parameter S_CHECK = 3'b001;
    parameter S_ADD   = 3'b010;
    parameter S_SHIFT = 3'b011;
    parameter S_END   = 3'b100;

    reg [2:0] state;
    reg [5:0] count_done;

// MÁQUINA DE ESTADOS

    always @(posedge clk or posedge reset) begin

        if (reset) begin
            state      <= S_START;
            count_done <= 6'd0;
        end
        else begin

            case (state)

                S_START: begin
                    count_done <= 6'd0;

                    if (init)
                        state <= S_CHECK;
                    else
                        state <= S_START;
                end

                S_CHECK: begin
                    if (C)
                        state <= S_END;
                    else if (LSB_B_process)
                        state <= S_ADD;
                    else
                        state <= S_SHIFT;
                end

                S_ADD: begin
                    state <= S_SHIFT;
                end

                S_SHIFT: begin
                    state <= S_CHECK;
                end

                S_END: begin
                    count_done <= count_done + 1;

                    if (count_done > 6'd30)
                        state <= S_START;
                    else
                        state <= S_END;
                end

                default: begin
                    state <= S_START;
                end

            endcase
        end
    end

// Logica de los estados

    always @(*) begin

        case (state)

            S_START: begin
                ADD_EN = 0;
                SH     = 0;
                DEC    = 0;
                LD     = 1;
                DONE   = 0;
            end

            S_CHECK: begin
                ADD_EN = 0;
                SH     = 0;
                DEC    = 0;
                LD     = 0;
                DONE   = 0;
            end

            S_ADD: begin
                ADD_EN = 1;
                SH     = 0;
                DEC    = 0;
                LD     = 0;
                DONE   = 0;
            end

            S_SHIFT: begin
                ADD_EN = 0;
                SH     = 1;
                DEC    = 1;
                LD     = 0;
                DONE   = 0;
            end

            S_END: begin
                ADD_EN = 0;
                SH     = 0;
                DEC    = 0;
                LD     = 0;
                DONE   = 1;
            end

            default: begin
                ADD_EN = 0;
                SH     = 0;
                DEC    = 0;
                LD     = 0;
                DONE   = 0;
            end

        endcase
    end

endmodule

Calculadora/rtl/Cores/Multiplicador/Comp_count_Multiplicador.v
module Comp_count_Multiplicador (
    input [4:0] count_out,
    output C
);

assign C = (count_out == 5'd0);

endmodule

Calculadora/rtl/Cores/Multiplicador/Count_Mulplicador.v
module Count_Multiplicador (
    input clk,
    input LD,
    input DEC,

    output reg [4:0] count_out
);

always @(posedge clk) begin
    if (LD) begin
        count_out <= 5'd16;
    end
    else if (DEC) begin
        count_out <= count_out - 1;
    end
end

endmodule

rtl/Cores/Multiplicador/Z.v
module Z (
    input clk,
    input LD,
    input ADD_EN,
    input [31:0] A_process_out,

    output reg [31:0] Z_out
);

always @(posedge clk) begin
    if (LD) begin
        Z_out <= 32'b0;
    end
    else if (ADD_EN) begin
        Z_out <= Z_out + A_process_out;
    end
end

endmodule

Calculadora/rtl/Cores/Multiplicador/B_process_Multiplicador.v
module B_process_Multiplicador (
    input clk,
    input LD,
    input SH,
    input [15:0] B,

    output reg [15:0] B_process_out,
    output LSB_B_process
);

assign LSB_B_process = B_process_out[0];

always @(posedge clk) begin
    if (LD) begin
        B_process_out <= B;
    end
    else if (SH) begin
        B_process_out <= B_process_out >> 1;
    end
end

endmodule

Calculadora/rtl/Cores/Multiplicador/A_process_Multiplicador.v
module A_process_Multiplicador (
    input clk,
    input LD,
    input SH,
    input [15:0] A,

    output reg [31:0] A_process_out
);

always @(posedge clk) begin
    if (LD) begin
        A_process_out <= {16'b0, A};
    end
    else if (SH) begin
        A_process_out <= A_process_out << 1;
    end
end

endmodule

Calculadora/rtl/Cores/Multiplicador/TOP_Multiplicador.v
module TOP_Multiplicador (

    input reset,
    input clk, 
    input init,


    input [15:0] A, // Multiplicando

    input [15:0] B, // Multiplicador

    output [31:0] Resultado,

    output DONE
);


// Señales in modulos
wire LD;
wire ADD_EN;
wire SH;
wire DEC;

// Señales out modulos
wire LSB_B_process;
wire C;

// Señales internas
wire [31:0] A_process_out;
wire [15:0] B_process_out;
wire [31:0] Z_out;
wire [4:0] count_out;



A_process_Multiplicador A_process_inst (
    .clk(clk),
    .LD(LD),
    .SH(SH),
    .A(A),
    .A_process_out(A_process_out)
);


B_process_Multiplicador B_process_inst (
    .clk(clk),
    .LD(LD),
    .SH(SH),
    .B(B),
    .B_process_out(B_process_out),
    .LSB_B_process(LSB_B_process)
);


Z Z_inst (
    .clk(clk),
    .LD(LD),
    .ADD_EN(ADD_EN),
    .A_process_out(A_process_out),
    .Z_out(Z_out)
);


Count_Multiplicador Count_inst (
    .clk(clk),
    .LD(LD),
    .DEC(DEC),
    .count_out(count_out)
);


Comp_count_Multiplicador Comp_count_inst (
    .count_out(count_out),
    .C(C)
);


Control_Multiplicador Control_inst (
    .clk(clk),
    .reset(reset),
    .init(init),
    .C(C),
    .LSB_B_process(LSB_B_process),

    .ADD_EN(ADD_EN),
    .SH(SH),
    .DEC(DEC),
    .LD(LD),
    .DONE(DONE)
);


assign Resultado = Z_out;

endmodule

Calculadora/rtl/Cores/Multiplicador/Periferico_Multiplicador.v
module Periferico_Multiplicador (
    input clk,
    input reset,

    input [15:0] d_in,
    input cs,
    input [4:0] addr,
    input rd,
    input wr,

    output reg [31:0] d_out
);

    // Selector interno de registros
    reg [4:0] s;

    // Registros internos del periférico
    reg [15:0] A;
    reg [15:0] B;
    reg init;

    // Salidas directas del TOP_Multiplicador
    wire [31:0] Resultado_top;
    wire DONE_top;

    // Registros de estado del periférico
    reg [31:0] Resultado_status;
    reg DONE_status;

    // Decodificador de direcciones
    always @(*) begin
        if (cs) begin
            case (addr)
                5'h04: s = 5'b00001; // A
                5'h08: s = 5'b00010; // B
                5'h0C: s = 5'b00100; // init
                5'h10: s = 5'b01000; // Resultado
                5'h14: s = 5'b10000; // DONE
                default: s = 5'b00000;
            endcase
        end
        else begin
            s = 5'b00000;
        end
    end

    // Escritura desde el procesador
    always @(posedge clk) begin
        if (reset) begin
            A    <= 16'b0;
            B    <= 16'b0;
            init <= 1'b0;
        end
        else begin
            if (cs && wr) begin

                if (s[0])
                    A <= d_in;

                if (s[1])
                    B <= d_in;

                if (s[2])
                    init <= d_in[0];

            end
        end
    end

    // Registro de resultado y DONE
    always @(posedge clk) begin

        if (reset) begin
            Resultado_status <= 32'b0;
            DONE_status      <= 1'b0;
        end
        else begin

            // Nueva operación
            if (cs && wr && s[2] && d_in[0]) begin
                DONE_status      <= 1'b0;
                Resultado_status <= 32'b0;
            end

            // Fin de operación
            if (DONE_top) begin
                Resultado_status <= Resultado_top;
                DONE_status      <= 1'b1;
            end

        end

    end

    // Lectura hacia el procesador
    always @(posedge clk) begin
        if (reset) begin
            d_out <= 32'b0;
        end
        else if (cs && rd) begin
            case (addr)
                5'h10: d_out <= Resultado_status;
                5'h14: d_out <= {31'b0, DONE_status};
                default: d_out <= 32'b0;
            endcase
        end
    end

    // Instancia del multiplicador
    TOP_Multiplicador u_mult (

        .reset(reset),
        .clk(clk),
        .init(init),

        .A(A),
        .B(B),

        .Resultado(Resultado_top),
        .DONE(DONE_top)

    );

endmodule

Calculadora/rtl/Cores/Multiplicador/Testbench_Periferico_Multiplicador.v
`timescale 1ns / 1ps

module Testbench_Periferico_Multiplicador;

    reg clk;
    reg reset;
    reg [15:0] d_in;
    reg cs;
    reg [4:0] addr;
    reg rd;
    reg wr;

    wire [31:0] d_out;

    Periferico_Multiplicador uut (
        .clk(clk),
        .reset(reset),
        .d_in(d_in),
        .cs(cs),
        .addr(addr),
        .rd(rd),
        .wr(wr),
        .d_out(d_out)
    );

    always begin
        #5 clk = ~clk;
    end

    initial begin
        $dumpfile("Periferico_Multiplicador.vcd");
        $dumpvars(0, Testbench_Periferico_Multiplicador);

        clk = 0;
        reset = 1;
        d_in = 0;
        cs = 0;
        addr = 0;
        rd = 0;
        wr = 0;

        #20;
        reset = 0;

        // A = 13
        @(posedge clk);
        cs = 1; wr = 1; rd = 0;
        addr = 5'h04;
        d_in = 16'd13;

        @(posedge clk);
        cs = 0; wr = 0;

        // B = 16
        @(posedge clk);
        cs = 1; wr = 1; rd = 0;
        addr = 5'h08;
        d_in = 16'd16;

        @(posedge clk);
        cs = 0; wr = 0;

        // init = 1
        @(posedge clk);
        cs = 1; wr = 1; rd = 0;
        addr = 5'h0C;
        d_in = 16'd1;

        @(posedge clk);
        cs = 0; wr = 0;

        // mantener init unos ciclos
        repeat (3) @(posedge clk);

        // init = 0
        @(posedge clk);
        cs = 1; wr = 1; rd = 0;
        addr = 5'h0C;
        d_in = 16'd0;

        @(posedge clk);
        cs = 0; wr = 0;

        // Esperar hasta que el multiplicador termine
        wait (uut.DONE_status == 1);

        // Leer DONE
        @(posedge clk);
        cs = 1; rd = 1; wr = 0;
        addr = 5'h14;

        #1;
        $display("DONE leido = %d", d_out);

        @(posedge clk);
        cs = 0; rd = 0;

        // Leer Resultado inmediatamente
        @(posedge clk);
        cs = 1; rd = 1; wr = 0;
        addr = 5'h10;

        #1;
        $display("Resultado leido = %d", d_out);

        @(posedge clk);
        cs = 0; rd = 0;

        #20;
        $finish;
    end


    //iverilog -s Testbench_Periferico_Multiplicador -o sim *.v
    //gtkwave Periferico_Multiplicador.vcd
    
endmodule

Calculadora/rtl/Cores/Multiplicador/Periferico_Multiplicador.vcd
$date
	Wed Jun 10 13:06:08 2026
$end
$version
	Icarus Verilog
$end
$timescale
	1ps
$end
$scope module Testbench_Periferico_Multiplicador $end
$var wire 32 ! d_out [31:0] $end
$var reg 5 " addr [4:0] $end
$var reg 1 # clk $end
$var reg 1 $ cs $end
$var reg 16 % d_in [15:0] $end
$var reg 1 & rd $end
$var reg 1 ' reset $end
$var reg 1 ( wr $end
$scope module uut $end
$var wire 5 ) addr [4:0] $end
$var wire 1 # clk $end
$var wire 1 $ cs $end
$var wire 16 * d_in [15:0] $end
$var wire 1 & rd $end
$var wire 1 ' reset $end
$var wire 1 ( wr $end
$var wire 32 + Resultado_top [31:0] $end
$var wire 1 , DONE_top $end
$var reg 16 - A [15:0] $end
$var reg 16 . B [15:0] $end
$var reg 1 / DONE_status $end
$var reg 32 0 Resultado_status [31:0] $end
$var reg 32 1 d_out [31:0] $end
$var reg 1 2 init $end
$var reg 5 3 s [4:0] $end
$scope module u_mult $end
$var wire 16 4 A [15:0] $end
$var wire 16 5 B [15:0] $end
$var wire 32 6 Resultado [31:0] $end
$var wire 1 # clk $end
$var wire 1 2 init $end
$var wire 1 ' reset $end
$var wire 5 7 count_out [4:0] $end
$var wire 32 8 Z_out [31:0] $end
$var wire 1 9 SH $end
$var wire 1 : LSB_B_process $end
$var wire 1 ; LD $end
$var wire 1 , DONE $end
$var wire 1 < DEC $end
$var wire 1 = C $end
$var wire 16 > B_process_out [15:0] $end
$var wire 32 ? A_process_out [31:0] $end
$var wire 1 @ ADD_EN $end
$scope module A_process_inst $end
$var wire 16 A A [15:0] $end
$var wire 1 # clk $end
$var wire 1 9 SH $end
$var wire 1 ; LD $end
$var reg 32 B A_process_out [31:0] $end
$upscope $end
$scope module B_process_inst $end
$var wire 16 C B [15:0] $end
$var wire 1 # clk $end
$var wire 1 9 SH $end
$var wire 1 : LSB_B_process $end
$var wire 1 ; LD $end
$var reg 16 D B_process_out [15:0] $end
$upscope $end
$scope module Comp_count_inst $end
$var wire 5 E count_out [4:0] $end
$var wire 1 = C $end
$upscope $end
$scope module Control_inst $end
$var wire 1 = C $end
$var wire 1 : LSB_B_process $end
$var wire 1 # clk $end
$var wire 1 2 init $end
$var wire 1 ' reset $end
$var parameter 3 F S_ADD $end
$var parameter 3 G S_CHECK $end
$var parameter 3 H S_END $end
$var parameter 3 I S_SHIFT $end
$var parameter 3 J S_START $end
$var reg 1 @ ADD_EN $end
$var reg 1 < DEC $end
$var reg 1 , DONE $end
$var reg 1 ; LD $end
$var reg 1 9 SH $end
$var reg 6 K count_done [5:0] $end
$var reg 3 L state [2:0] $end
$upscope $end
$scope module Count_inst $end
$var wire 1 < DEC $end
$var wire 1 ; LD $end
$var wire 1 # clk $end
$var reg 5 M count_out [4:0] $end
$upscope $end
$scope module Z_inst $end
$var wire 1 @ ADD_EN $end
$var wire 32 N A_process_out [31:0] $end
$var wire 1 ; LD $end
$var wire 1 # clk $end
$var reg 32 O Z_out [31:0] $end
$upscope $end
$upscope $end
$upscope $end
$upscope $end
$enddefinitions $end
$comment Show the parameter values. $end
$dumpall
b0 J
b11 I
b100 H
b1 G
b10 F
$end
#0
$dumpvars
bx O
bx N
bx M
b0 L
b0 K
bx E
bx D
bx C
bx B
bx A
0@
bx ?
bx >
x=
0<
1;
x:
09
bx 8
bx 7
bx 6
bx 5
bx 4
b0 3
x2
bx 1
bx 0
x/
bx .
bx -
0,
bx +
b0 *
b0 )
0(
1'
0&
b0 %
0$
0#
b0 "
bx !
$end
#5000
b0xxxxxxxxxxxxxxxx ?
b0xxxxxxxxxxxxxxxx B
b0xxxxxxxxxxxxxxxx N
b0 +
b0 6
b0 8
b0 O
0=
b10000 7
b10000 E
b10000 M
02
b0 .
b0 5
b0 C
b0 -
b0 4
b0 A
0/
b0 0
b0 !
b0 1
1#
#10000
0#
#15000
0:
b0 >
b0 D
b0 ?
b0 B
b0 N
1#
#20000
0#
0'
#25000
b1 3
b1101 %
b1101 *
b100 "
b100 )
1(
1$
1#
#30000
0#
#35000
b1101 -
b1101 4
b1101 A
b0 3
0(
0$
1#
#40000
0#
#45000
b1101 ?
b1101 B
b1101 N
b10 3
b10000 %
b10000 *
b1000 "
b1000 )
1(
1$
1#
#50000
0#
#55000
b10000 .
b10000 5
b10000 C
b0 3
0(
0$
1#
#60000
0#
#65000
b10000 >
b10000 D
b100 3
b1 %
b1 *
b1100 "
b1100 )
1(
1$
1#
#70000
0#
#75000
12
b0 3
0(
0$
1#
#80000
0#
#85000
0;
b1 L
1#
#90000
0#
#95000
1<
19
b11 L
1#
#100000
0#
#105000
0<
09
b11010 ?
b11010 B
b11010 N
b1000 >
b1000 D
b1111 7
b1111 E
b1111 M
b1 L
1#
#110000
0#
#115000
1<
19
b11 L
b100 3
b0 %
b0 *
1(
1$
1#
#120000
0#
#125000
0<
09
b110100 ?
b110100 B
b110100 N
b100 >
b100 D
b1110 7
b1110 E
b1110 M
b1 L
b0 3
0(
0$
1#
#130000
0#
#135000
1<
19
b11 L
1#
#140000
0#
#145000
0<
09
b1101000 ?
b1101000 B
b1101000 N
b10 >
b10 D
b1101 7
b1101 E
b1101 M
b1 L
1#
#150000
0#
#155000
1<
19
b11 L
1#
#160000
0#
#165000
1:
0<
09
b11010000 ?
b11010000 B
b11010000 N
b1 >
b1 D
b1100 7
b1100 E
b1100 M
b1 L
1#
#170000
0#
#175000
1@
b10 L
1#
#180000
0#
#185000
1<
19
0@
b11010000 +
b11010000 6
b11010000 8
b11010000 O
b11 L
1#
#190000
0#
#195000
0:
0<
09
b1011 7
b1011 E
b1011 M
b0 >
b0 D
b110100000 ?
b110100000 B
b110100000 N
b1 L
1#
#200000
0#
#205000
1<
19
b11 L
1#
#210000
0#
#215000
0<
09
b1010 7
b1010 E
b1010 M
b1101000000 ?
b1101000000 B
b1101000000 N
b1 L
1#
#220000
0#
#225000
1<
19
b11 L
1#
#230000
0#
#235000
0<
09
b1001 7
b1001 E
b1001 M
b11010000000 ?
b11010000000 B
b11010000000 N
b1 L
1#
#240000
0#
#245000
1<
19
b11 L
1#
#250000
0#
#255000
0<
09
b1000 7
b1000 E
b1000 M
b110100000000 ?
b110100000000 B
b110100000000 N
b1 L
1#
#260000
0#
#265000
1<
19
b11 L
1#
#270000
0#
#275000
0<
09
b111 7
b111 E
b111 M
b1101000000000 ?
b1101000000000 B
b1101000000000 N
b1 L
1#
#280000
0#
#285000
1<
19
b11 L
1#
#290000
0#
#295000
0<
09
b110 7
b110 E
b110 M
b11010000000000 ?
b11010000000000 B
b11010000000000 N
b1 L
1#
#300000
0#
#305000
1<
19
b11 L
1#
#310000
0#
#315000
0<
09
b101 7
b101 E
b101 M
b110100000000000 ?
b110100000000000 B
b110100000000000 N
b1 L
1#
#320000
0#
#325000
1<
19
b11 L
1#
#330000
0#
#335000
0<
09
b100 7
b100 E
b100 M
b1101000000000000 ?
b1101000000000000 B
b1101000000000000 N
b1 L
1#
#340000
0#
#345000
1<
19
b11 L
1#
#350000
0#
#355000
0<
09
b11 7
b11 E
b11 M
b11010000000000000 ?
b11010000000000000 B
b11010000000000000 N
b1 L
1#
#360000
0#
#365000
1<
19
b11 L
1#
#370000
0#
#375000
0<
09
b10 7
b10 E
b10 M
b110100000000000000 ?
b110100000000000000 B
b110100000000000000 N
b1 L
1#
#380000
0#
#385000
1<
19
b11 L
1#
#390000
0#
#395000
0<
09
b1 7
b1 E
b1 M
b1101000000000000000 ?
b1101000000000000000 B
b1101000000000000000 N
b1 L
1#
#400000
0#
#405000
1<
19
b11 L
1#
#410000
0#
#415000
0<
09
1=
b0 7
b0 E
b0 M
b11010000000000000000 ?
b11010000000000000000 B
b11010000000000000000 N
b1 L
1#
#420000
0#
#425000
1,
b100 L
1#
#430000
0#
#435000
1/
b11010000 0
b1 K
1#
#440000
0#
#445000
b1 !
b1 1
b10 K
b10000 3
b10100 "
b10100 )
1&
1$
1#
#450000
0#
#455000
b11 K
b0 3
0&
0$
1#
#460000
0#
#465000
b100 K
b1000 3
b10000 "
b10000 )
1&
1$
1#
#470000
0#
#475000
b101 K
b0 3
0&
0$
1#
#480000
0#
#485000
b110 K
1#
#490000
0#
#495000
b111 K
1#
