rtl/Cores/Binario a BCD/Control_BinarioBCD.v
module Control_BinarioBCD (
    input clk,
    input reset,
    input init,
    input M,
    input C,
    output reg LD,
    output reg SH,
    output reg ADD3,
    output reg DEC,
    output reg DONE
);

    parameter START       = 3'b000;
    parameter CHECK_BCD   = 3'b001;
    parameter ADD3_STATE  = 3'b010;
    parameter SHIFT       = 3'b011;
    parameter DEC_COUNT   = 3'b100;
    parameter CHECK_COUNT = 3'b101;
    parameter END_STATE   = 3'b110;

    reg [2:0] state;

    always @(posedge clk) begin
        if (reset) begin
            state <= START;
        end
        else begin
            case (state)
                START: begin
                    if (init)
                        state <= CHECK_BCD;
                    else
                        state <= START;
                end

                CHECK_BCD: begin
                    if (M)
                        state <= ADD3_STATE;
                    else
                        state <= SHIFT;
                end

                ADD3_STATE: begin
                    state <= SHIFT;
                end

                SHIFT: begin
                    state <= DEC_COUNT;
                end

                DEC_COUNT: begin
                    state <= CHECK_COUNT;
                end

                CHECK_COUNT: begin
                    if (C)
                        state <= CHECK_BCD;
                    else
                        state <= END_STATE;
                end

                END_STATE: begin
                    state <= START;
                end

                default: begin
                    state <= START;
                end
            endcase
        end
    end

    always @(*) begin
        LD    = 0;
        SH    = 0;
        ADD3  = 0;
        DEC   = 0;
        DONE  = 0;

        case (state)
            START: begin
                LD    = 1;
                SH    = 0;
                ADD3  = 0;
                DEC   = 0;
                DONE  = 0;
            end

            CHECK_BCD: begin
                LD    = 0;
                SH    = 0;
                ADD3  = 0;
                DEC   = 0;
                DONE  = 0;
            end

            ADD3_STATE: begin
                LD    = 0;
                SH    = 0;
                ADD3  = 1;
                DEC   = 0;
                DONE  = 0;
            end

            SHIFT: begin
                LD    = 0;
                SH    = 1;
                ADD3  = 0;
                DEC   = 0;
                DONE  = 0;
            end

            DEC_COUNT: begin
                LD    = 0;
                SH    = 0;
                ADD3  = 0;
                DEC   = 1;
                DONE  = 0;
            end

            CHECK_COUNT: begin
                LD    = 0;
                SH    = 0;
                ADD3  = 0;
                DEC   = 0;
                DONE  = 0;
            end

            END_STATE: begin
                LD    = 0;
                SH    = 0;
                ADD3  = 0;
                DEC   = 0;
                DONE  = 1;
            end
        endcase
    end

endmodule

rtl/Cores/Binario a BCD/Comp_count_BinarioBCD.v
module Comp_count_BinarioBCD (
    input [5:0] count,
    output C
);

    assign C = (count != 6'd0);

endmodule

Calculadora/rtl/Cores/Binario_BCD/Count_BinarioBCD.v
module Count_BinarioBCD (
    input clk,
    input LD,
    input DEC,
    output reg [5:0] count
);

    always @(posedge clk) begin
        if (LD) begin
            count <= 6'd32;
        end
        else if (DEC) begin
            count <= count - 1'b1;
        end
        else begin
            count <= count;
        end
    end

endmodule

Calculadora/rtl/Cores/Binario_BCD/Comparador_BCD.v
module Comparador_BCD (
    input [31:0] BCD_in,
    
    output [7:0] M_digit,
    output M
);

    assign M_digit[0] = (BCD_in[3:0]   > 4'd4);
    assign M_digit[1] = (BCD_in[7:4]   > 4'd4);
    assign M_digit[2] = (BCD_in[11:8]  > 4'd4);
    assign M_digit[3] = (BCD_in[15:12] > 4'd4);
    assign M_digit[4] = (BCD_in[19:16] > 4'd4);
    assign M_digit[5] = (BCD_in[23:20] > 4'd4);
    assign M_digit[6] = (BCD_in[27:24] > 4'd4);
    assign M_digit[7] = (BCD_in[31:28] > 4'd4);

    assign M = |M_digit;

endmodule

Calculadora/rtl/Cores/Binario_BCD/BCD.v
module BCD (
    input clk,
    input LD,
    input SH,
    input ADD3,
    input MSB_A,
    input [7:0] M_digit,
    
    output reg [31:0] BCD_out
);

    always @(posedge clk) begin
        if (LD) begin
            BCD_out <= 32'd0;
        end
        else if (ADD3) begin
            BCD_out[3:0]   <= M_digit[0] ? BCD_out[3:0]   + 4'd3 : BCD_out[3:0];
            BCD_out[7:4]   <= M_digit[1] ? BCD_out[7:4]   + 4'd3 : BCD_out[7:4];
            BCD_out[11:8]  <= M_digit[2] ? BCD_out[11:8]  + 4'd3 : BCD_out[11:8];
            BCD_out[15:12] <= M_digit[3] ? BCD_out[15:12] + 4'd3 : BCD_out[15:12];
            BCD_out[19:16] <= M_digit[4] ? BCD_out[19:16] + 4'd3 : BCD_out[19:16];
            BCD_out[23:20] <= M_digit[5] ? BCD_out[23:20] + 4'd3 : BCD_out[23:20];
            BCD_out[27:24] <= M_digit[6] ? BCD_out[27:24] + 4'd3 : BCD_out[27:24];
            BCD_out[31:28] <= M_digit[7] ? BCD_out[31:28] + 4'd3 : BCD_out[31:28];
        end
        else if (SH) begin
            BCD_out <= {BCD_out[30:0], MSB_A};
        end
        else begin
            BCD_out <= BCD_out;
        end
    end

endmodule

Calculadora/rtl/Cores/Binario_BCD/A_process_BinarioBCD.v
module A_process_BinarioBCD (
    input clk,
    input LD,
    input SH,
    input [31:0] A,
    output reg [31:0] A_out,
    output MSB_A
);

    assign MSB_A = A_out[31];

    always @(posedge clk) begin
        if (LD) begin
            A_out <= A;
        end
        else if (SH) begin
            A_out <= A_out << 1;
        end
        else begin
            A_out <= A_out;
        end
    end

endmodule

Calculadora/rtl/Cores/Binario_BCD/TOP_BinarioBCD.v
module TOP_BinarioBCD (
    input clk,
    input reset,
    input init,
    input [31:0] A,
    output [31:0] BCD,
    output DONE
);

    wire LD;
    wire SH;
    wire ADD3;
    wire DEC;

    wire [31:0] A_out;
    wire MSB_A;

    wire [31:0] BCD_out;

    wire [7:0] M_digit;
    wire M;

    wire [5:0] count;
    wire C;

    A_process_BinarioBCD U1 (
        .clk(clk),
        .LD(LD),
        .SH(SH),
        .A(A),
        .A_out(A_out),
        .MSB_A(MSB_A)
    );

    BCD U2 (
        .clk(clk),
        .LD(LD),
        .SH(SH),
        .ADD3(ADD3),
        .MSB_A(MSB_A),
        .M_digit(M_digit),
        .BCD_out(BCD_out)
    );

    Comparador_BCD U3 (
        .BCD_in(BCD_out),
        .M_digit(M_digit),
        .M(M)
    );

    Count_BinarioBCD U4 (
        .clk(clk),
        .LD(LD),
        .DEC(DEC),
        .count(count)
    );

    Comp_count_BinarioBCD U5 (
        .count(count),
        .C(C)
    );

    Control_BinarioBCD U6 (
        .clk(clk),
        .reset(reset),
        .init(init),
        .M(M),
        .C(C),
        .LD(LD),
        .SH(SH),
        .ADD3(ADD3),
        .DEC(DEC),
        .DONE(DONE)
    );

    assign BCD = BCD_out;

endmodule

Calculadora/rtl/Cores/Binario_BCD/Periferico_BinarioBCD.v
module Periferico_BinarioBCD (
    input clk,
    input reset,

    input [31:0] d_in,
    input cs,
    input [4:0] addr,
    input rd,
    input wr,

    output reg [31:0] d_out
);

    reg [3:0] s;

    reg [31:0] A_reg;
    reg init;

    wire [31:0] BCD_wire;
    wire DONE_wire;

    reg [31:0] BCD_reg;
    reg DONE_reg;

    always @(*) begin
        if (cs) begin
            case (addr)
                5'h04: s = 4'b0001; // A
                5'h08: s = 4'b0010; // init
                5'h0C: s = 4'b0100; // Resultado BCD
                5'h10: s = 4'b1000; // DONE
                default: s = 4'b0000;
            endcase
        end
        else begin
            s = 4'b0000;
        end
    end

    always @(posedge clk) begin
        if (reset) begin
            A_reg    <= 32'b0;
            init     <= 1'b0;
            BCD_reg  <= 32'b0;
            DONE_reg <= 1'b0;
        end
        else begin

            if (cs && wr) begin
                if (s[0])
                    A_reg <= d_in;

                if (s[1]) begin
                    init <= d_in[0];

                    if (d_in[0] == 1'b1) begin
                        DONE_reg <= 1'b0;
                        BCD_reg  <= 32'b0;
                    end
                end
            end

            if (DONE_wire) begin
                BCD_reg  <= BCD_wire;
                DONE_reg <= 1'b1;
            end

        end
    end



    always @(posedge clk) begin
        if (reset) begin
            d_out <= 32'b0;
        end
        else if (cs && rd) begin
            case (addr)
                5'h0C: d_out <= BCD_reg;
                5'h10: d_out <= {31'b0, DONE_reg};
                default: d_out <= 32'b0;
            endcase
        end
    end


    TOP_BinarioBCD U_TOP_BINBCD (
        .clk(clk),
        .reset(reset),
        .init(init),
        .A(A_reg),
        .BCD(BCD_wire),
        .DONE(DONE_wire)
    );

endmodule

rtl/Cores/Binario a BCD/Testbench_Periferico_BinarioBCD.v
`timescale 1ns / 1ps

module Testbench_Periferico_BinarioBCD;

    reg clk;
    reg reset;

    reg [31:0] d_in;
    reg cs;
    reg [4:0] addr;
    reg rd;
    reg wr;

    wire [31:0] d_out;

    reg [31:0] DONE;
    reg [31:0] Resultado_BCD;

    Periferico_BinarioBCD uut (
        .clk(clk),
        .reset(reset),
        .d_in(d_in),
        .cs(cs),
        .addr(addr),
        .rd(rd),
        .wr(wr),
        .d_out(d_out)
    );

    always #10 clk = ~clk;

    task write_reg;
        input [4:0] address;
        input [31:0] data;
        begin
            @(posedge clk);
            cs   = 1;
            wr   = 1;
            rd   = 0;
            addr = address;
            d_in = data;

            @(posedge clk);
            cs   = 0;
            wr   = 0;
            addr = 5'h00;
            d_in = 32'h00000000;
        end
    endtask

    task read_reg;
        input [4:0] address;
        output [31:0] data;
        begin
            @(posedge clk);
            cs   = 1;
            rd   = 1;
            wr   = 0;
            addr = address;

            #1;
            data = d_out;

            @(posedge clk);
            cs   = 0;
            rd   = 0;
            addr = 5'h00;
        end
    endtask

    task run_test;
        input [31:0] entrada;
        input [31:0] esperado;
        begin
            write_reg(5'h04, entrada);

            write_reg(5'h08, 32'd1);
            write_reg(5'h08, 32'd0);

            DONE = 32'd0;

            while (DONE[0] == 1'b0) begin
                read_reg(5'h10, DONE);
            end

            read_reg(5'h0C, Resultado_BCD);

            $display("----------------------------------");
            $display("PERIFERICO");
            $display("Entrada decimal = %0d", entrada);
            $display("Entrada binaria = %032b", entrada);
            $display("DONE            = %0d", DONE[0]);
            $display("Resultado BCD h = %h", Resultado_BCD);
            $display("Resultado BCD b = %032b", Resultado_BCD);
            $display("BCD esperado h  = %h", esperado);

            if (Resultado_BCD == esperado)
                $display("PRUEBA PERIFERICO OK");
            else
                $display("PRUEBA PERIFERICO ERROR");
        end
    endtask

    initial begin
        $dumpfile("Testbench_Periferico_BinarioBCD.vcd");
        $dumpvars(0, Testbench_Periferico_BinarioBCD);

        clk = 0;
        reset = 1;
        d_in = 0;
        cs = 0;
        addr = 0;
        rd = 0;
        wr = 0;
        DONE = 0;
        Resultado_BCD = 0;

        #50;
        reset = 0;

        run_test(32'd820, 32'h820);
        

        #100;
        $finish;
    end

endmodule

//iverilog -s Testbench_Periferico_BinarioBCD -o sim *.v
//gtkwave Testbench_Periferico_BinarioBCD.vcd

Calculadora/rtl/Cores/Binario_BCD/Testbench_Periferico_BinarioBCD.vcd
$date
	Tue Jun  9 11:31:33 2026
$end
$version
	Icarus Verilog
$end
$timescale
	1ps
$end
$scope module Testbench_Periferico_BinarioBCD $end
$var wire 32 ! d_out [31:0] $end
$var reg 32 " DONE [31:0] $end
$var reg 32 # Resultado_BCD [31:0] $end
$var reg 5 $ addr [4:0] $end
$var reg 1 % clk $end
$var reg 1 & cs $end
$var reg 32 ' d_in [31:0] $end
$var reg 1 ( rd $end
$var reg 1 ) reset $end
$var reg 1 * wr $end
$scope module uut $end
$var wire 5 + addr [4:0] $end
$var wire 1 % clk $end
$var wire 1 & cs $end
$var wire 32 , d_in [31:0] $end
$var wire 1 ( rd $end
$var wire 1 ) reset $end
$var wire 1 * wr $end
$var wire 1 - DONE_wire $end
$var wire 32 . BCD_wire [31:0] $end
$var reg 32 / A_reg [31:0] $end
$var reg 32 0 BCD_reg [31:0] $end
$var reg 1 1 DONE_reg $end
$var reg 32 2 d_out [31:0] $end
$var reg 1 3 init $end
$var reg 4 4 s [3:0] $end
$scope module U_TOP_BINBCD $end
$var wire 32 5 A [31:0] $end
$var wire 32 6 BCD [31:0] $end
$var wire 1 % clk $end
$var wire 1 3 init $end
$var wire 1 ) reset $end
$var wire 6 7 count [5:0] $end
$var wire 1 8 SH $end
$var wire 8 9 M_digit [7:0] $end
$var wire 1 : MSB_A $end
$var wire 1 ; M $end
$var wire 1 < LD $end
$var wire 1 - DONE $end
$var wire 1 = DEC $end
$var wire 1 > C $end
$var wire 32 ? BCD_out [31:0] $end
$var wire 32 @ A_out [31:0] $end
$var wire 1 A ADD3 $end
$scope module U1 $end
$var wire 32 B A [31:0] $end
$var wire 1 % clk $end
$var wire 1 8 SH $end
$var wire 1 : MSB_A $end
$var wire 1 < LD $end
$var reg 32 C A_out [31:0] $end
$upscope $end
$scope module U2 $end
$var wire 1 : MSB_A $end
$var wire 1 % clk $end
$var wire 1 8 SH $end
$var wire 8 D M_digit [7:0] $end
$var wire 1 < LD $end
$var wire 1 A ADD3 $end
$var reg 32 E BCD_out [31:0] $end
$upscope $end
$scope module U3 $end
$var wire 32 F BCD_in [31:0] $end
$var wire 8 G M_digit [7:0] $end
$var wire 1 ; M $end
$upscope $end
$scope module U4 $end
$var wire 1 % clk $end
$var wire 1 < LD $end
$var wire 1 = DEC $end
$var reg 6 H count [5:0] $end
$upscope $end
$scope module U5 $end
$var wire 6 I count [5:0] $end
$var wire 1 > C $end
$upscope $end
$scope module U6 $end
$var wire 1 > C $end
$var wire 1 ; M $end
$var wire 1 % clk $end
$var wire 1 3 init $end
$var wire 1 ) reset $end
$var parameter 3 J ADD3_STATE $end
$var parameter 3 K CHECK_BCD $end
$var parameter 3 L CHECK_COUNT $end
$var parameter 3 M DEC_COUNT $end
$var parameter 3 N END_STATE $end
$var parameter 3 O SHIFT $end
$var parameter 3 P START $end
$var reg 1 A ADD3 $end
$var reg 1 = DEC $end
$var reg 1 - DONE $end
$var reg 1 < LD $end
$var reg 1 8 SH $end
$var reg 3 Q state [2:0] $end
$upscope $end
$upscope $end
$upscope $end
$scope task read_reg $end
$var reg 5 R address [4:0] $end
$var reg 32 S data [31:0] $end
$upscope $end
$scope task run_test $end
$var reg 32 T entrada [31:0] $end
$var reg 32 U esperado [31:0] $end
$upscope $end
$scope task write_reg $end
$var reg 5 V address [4:0] $end
$var reg 32 W data [31:0] $end
$upscope $end
$upscope $end
$enddefinitions $end
$comment Show the parameter values. $end
$dumpall
b0 P
b11 O
b110 N
b100 M
b101 L
b1 K
b10 J
$end
#0
$dumpvars
bx W
bx V
bx U
bx T
bx S
bx R
bx Q
bx I
bx H
bx G
bx F
bx E
bx D
bx C
bx B
xA
bx @
bx ?
x>
x=
x<
x;
x:
bx 9
x8
bx 7
bx 6
bx 5
b0 4
x3
b0 2
x1
bx 0
bx /
bx .
x-
b0 ,
b0 +
0*
1)
0(
b0 '
0&
0%
b0 $
b0 #
b0 "
b0 !
$end
#10000
0-
0=
0A
08
1<
b0 Q
01
b0 0
03
b0 /
b0 5
b0 B
1%
#20000
0%
#30000
0;
b0 9
b0 D
b0 G
0:
1>
b100000 7
b100000 H
b100000 I
b0 .
b0 6
b0 ?
b0 E
b0 F
b0 @
b0 C
1%
#40000
0%
#50000
b1 4
b1100110100 '
b1100110100 ,
b100 $
b100 +
1*
1&
1%
b1100110100 W
b100 V
b100000100000 U
b1100110100 T
0)
#60000
0%
#70000
b1100110100 /
b1100110100 5
b1100110100 B
b0 4
b1 W
b1000 V
b0 '
b0 ,
b0 $
b0 +
0*
0&
1%
#80000
0%
#90000
b1100110100 @
b1100110100 C
b10 4
b1 '
b1 ,
b1000 $
b1000 +
1*
1&
1%
#100000
0%
#110000
13
b0 4
b0 W
b0 '
b0 ,
b0 $
b0 +
0*
0&
1%
#120000
0%
#130000
0<
b1 Q
b10 4
b1000 $
b1000 +
1*
1&
1%
#140000
0%
#150000
18
03
b11 Q
b0 4
b10000 R
b0 $
b0 +
0*
0&
1%
#160000
0%
#170000
1=
08
b11001101000 @
b11001101000 C
b100 Q
b1000 4
b10000 $
b10000 +
1(
1&
1%
#171000
b0 S
#180000
0%
#190000
0=
b101 Q
b11111 7
b11111 H
b11111 I
b0 4
b0 $
b0 +
0(
0&
1%
#200000
0%
#210000
b1 Q
b1000 4
b10000 $
b10000 +
1(
1&
1%
#220000
0%
#230000
18
b11 Q
b0 4
b0 $
b0 +
0(
0&
1%
#240000
0%
#250000
1=
08
b110011010000 @
b110011010000 C
b100 Q
b1000 4
b10000 $
b10000 +
1(
1&
1%
#260000
0%
#270000
0=
b101 Q
b11110 7
b11110 H
b11110 I
b0 4
b0 $
b0 +
0(
0&
1%
#280000
0%
#290000
b1 Q
b1000 4
b10000 $
b10000 +
1(
1&
1%
#300000
0%
#310000
18
b11 Q
b0 4
b0 $
b0 +
0(
0&
1%
#320000
0%
#330000
1=
08
b1100110100000 @
b1100110100000 C
b100 Q
b1000 4
b10000 $
b10000 +
1(
1&
1%
#340000
0%
#350000
0=
b101 Q
b11101 7
b11101 H
b11101 I
b0 4
b0 $
b0 +
0(
0&
1%
#360000
0%
#370000
b1 Q
b1000 4
b10000 $
b10000 +
1(
1&
1%
#380000
0%
#390000
18
b11 Q
b0 4
b0 $
b0 +
0(
0&
1%
#400000
0%
#410000
1=
08
b11001101000000 @
b11001101000000 C
b100 Q
b1000 4
b10000 $
b10000 +
1(
1&
1%
#420000
0%
#430000
0=
b101 Q
b11100 7
b11100 H
b11100 I
b0 4
b0 $
b0 +
0(
0&
1%
#440000
0%
#450000
b1 Q
b1000 4
b10000 $
b10000 +
1(
1&
1%
#460000
0%
#470000
18
b11 Q
b0 4
b0 $
b0 +
0(
0&
1%
#480000
0%
#490000
1=
08
b110011010000000 @
b110011010000000 C
b100 Q
b1000 4
b10000 $
b10000 +
1(
1&
1%
#500000
0%
#510000
0=
b101 Q
b11011 7
b11011 H
b11011 I
b0 4
b0 $
b0 +
0(
0&
1%
#520000
0%
#530000
b1 Q
b1000 4
b10000 $
b10000 +
1(
1&
1%
#540000
0%
#550000
18
b11 Q
b0 4
b0 $
b0 +
0(
0&
1%
#560000
0%
#570000
1=
08
b1100110100000000 @
b1100110100000000 C
b100 Q
b1000 4
b10000 $
b10000 +
1(
1&
1%
#580000
0%
#590000
0=
b101 Q
b11010 7
b11010 H
b11010 I
b0 4
b0 $
b0 +
0(
0&
1%
#600000
0%
#610000
b1 Q
b1000 4
b10000 $
b10000 +
1(
1&
1%
#620000
0%
#630000
18
b11 Q
b0 4
b0 $
b0 +
0(
0&
1%
#640000
0%
#650000
1=
08
b11001101000000000 @
b11001101000000000 C
b100 Q
b1000 4
b10000 $
b10000 +
1(
1&
1%
#660000
0%
#670000
0=
b101 Q
b11001 7
b11001 H
b11001 I
b0 4
b0 $
b0 +
0(
0&
1%
#680000
0%
#690000
b1 Q
b1000 4
b10000 $
b10000 +
1(
1&
1%
#700000
0%
#710000
18
b11 Q
b0 4
b0 $
b0 +
0(
0&
1%
#720000
0%
#730000
1=
08
b110011010000000000 @
b110011010000000000 C
b100 Q
b1000 4
b10000 $
b10000 +
1(
1&
1%
#740000
0%
#750000
0=
b101 Q
b11000 7
b11000 H
b11000 I
b0 4
b0 $
b0 +
0(
0&
1%
#760000
0%
#770000
b1 Q
b1000 4
b10000 $
b10000 +
1(
1&
1%
#780000
0%
#790000
18
b11 Q
b0 4
b0 $
b0 +
0(
0&
1%
#800000
0%
#810000
1=
08
b1100110100000000000 @
b1100110100000000000 C
b100 Q
b1000 4
b10000 $
b10000 +
1(
1&
1%
#820000
0%
#830000
0=
b101 Q
b10111 7
b10111 H
b10111 I
b0 4
b0 $
b0 +
0(
0&
1%
#840000
0%
#850000
b1 Q
b1000 4
b10000 $
b10000 +
1(
1&
1%
#860000
0%
#870000
18
b11 Q
b0 4
b0 $
b0 +
0(
0&
1%
#880000
0%
#890000
1=
08
b11001101000000000000 @
b11001101000000000000 C
b100 Q
b1000 4
b10000 $
b10000 +
1(
1&
1%
#900000
0%
#910000
0=
b101 Q
b10110 7
b10110 H
b10110 I
b0 4
b0 $
b0 +
0(
0&
1%
#920000
0%
#930000
b1 Q
b1000 4
b10000 $
b10000 +
1(
1&
1%
#940000
0%
#950000
18
b11 Q
b0 4
b0 $
b0 +
0(
0&
1%
#960000
0%
#970000
1=
08
b110011010000000000000 @
b110011010000000000000 C
b100 Q
b1000 4
b10000 $
b10000 +
1(
1&
1%
#980000
0%
#990000
0=
b101 Q
b10101 7
b10101 H
b10101 I
b0 4
b0 $
b0 +
0(
0&
1%
#1000000
0%
#1010000
b1 Q
b1000 4
b10000 $
b10000 +
1(
1&
1%
#1020000
0%
#1030000
18
b11 Q
b0 4
b0 $
b0 +
0(
0&
1%
#1040000
0%
#1050000
1=
08
b1100110100000000000000 @
b1100110100000000000000 C
b100 Q
b1000 4
b10000 $
b10000 +
1(
1&
1%
#1060000
0%
#1070000
0=
b101 Q
b10100 7
b10100 H
b10100 I
b0 4
b0 $
b0 +
0(
0&
1%
#1080000
0%
#1090000
b1 Q
b1000 4
b10000 $
b10000 +
1(
1&
1%
#1100000
0%
#1110000
18
b11 Q
b0 4
b0 $
b0 +
0(
0&
1%
#1120000
0%
#1130000
1=
08
b11001101000000000000000 @
b11001101000000000000000 C
b100 Q
b1000 4
b10000 $
b10000 +
1(
1&
1%
#1140000
0%
#1150000
0=
b101 Q
b10011 7
b10011 H
b10011 I
b0 4
b0 $
b0 +
0(
0&
1%
#1160000
0%
#1170000
b1 Q
b1000 4
b10000 $
b10000 +
1(
1&
1%
#1180000
0%
#1190000
18
b11 Q
b0 4
b0 $
b0 +
0(
0&
1%
#1200000
0%
#1210000
1=
08
b110011010000000000000000 @
b110011010000000000000000 C
b100 Q
b1000 4
b10000 $
b10000 +
1(
1&
1%
#1220000
0%
#1230000
0=
b101 Q
b10010 7
b10010 H
b10010 I
b0 4
b0 $
b0 +
0(
0&
1%
#1240000
0%
#1250000
b1 Q
b1000 4
b10000 $
b10000 +
1(
1&
1%
#1260000
0%
#1270000
18
b11 Q
b0 4
b0 $
b0 +
0(
0&
1%
#1280000
0%
#1290000
1=
08
b1100110100000000000000000 @
b1100110100000000000000000 C
b100 Q
b1000 4
b10000 $
b10000 +
1(
1&
1%
#1300000
0%
#1310000
0=
b101 Q
b10001 7
b10001 H
b10001 I
b0 4
b0 $
b0 +
0(
0&
1%
#1320000
0%
#1330000
b1 Q
b1000 4
b10000 $
b10000 +
1(
1&
1%
#1340000
0%
#1350000
18
b11 Q
b0 4
b0 $
b0 +
0(
0&
1%
#1360000
0%
#1370000
1=
08
b11001101000000000000000000 @
b11001101000000000000000000 C
b100 Q
b1000 4
b10000 $
b10000 +
1(
1&
1%
#1380000
0%
#1390000
0=
b101 Q
b10000 7
b10000 H
b10000 I
b0 4
b0 $
b0 +
0(
0&
1%
#1400000
0%
#1410000
b1 Q
b1000 4
b10000 $
b10000 +
1(
1&
1%
#1420000
0%
#1430000
18
b11 Q
b0 4
b0 $
b0 +
0(
0&
1%
#1440000
0%
#1450000
1=
08
b110011010000000000000000000 @
b110011010000000000000000000 C
b100 Q
b1000 4
b10000 $
b10000 +
1(
1&
1%
#1460000
0%
#1470000
0=
b101 Q
b1111 7
b1111 H
b1111 I
b0 4
b0 $
b0 +
0(
0&
1%
#1480000
0%
#1490000
b1 Q
b1000 4
b10000 $
b10000 +
1(
1&
1%
#1500000
0%
#1510000
18
b11 Q
b0 4
b0 $
b0 +
0(
0&
1%
#1520000
0%
#1530000
1=
08
b1100110100000000000000000000 @
b1100110100000000000000000000 C
b100 Q
b1000 4
b10000 $
b10000 +
1(
1&
1%
#1540000
0%
#1550000
0=
b101 Q
b1110 7
b1110 H
b1110 I
b0 4
b0 $
b0 +
0(
0&
1%
#1560000
0%
#1570000
b1 Q
b1000 4
b10000 $
b10000 +
1(
1&
1%
#1580000
0%
#1590000
18
b11 Q
b0 4
b0 $
b0 +
0(
0&
1%
#1600000
0%
#1610000
1=
08
b11001101000000000000000000000 @
b11001101000000000000000000000 C
b100 Q
b1000 4
b10000 $
b10000 +
1(
1&
1%
#1620000
0%
#1630000
0=
b101 Q
b1101 7
b1101 H
b1101 I
b0 4
b0 $
b0 +
0(
0&
1%
#1640000
0%
#1650000
b1 Q
b1000 4
b10000 $
b10000 +
1(
1&
1%
#1660000
0%
#1670000
18
b11 Q
b0 4
b0 $
b0 +
0(
0&
1%
#1680000
0%
#1690000
1=
08
b110011010000000000000000000000 @
b110011010000000000000000000000 C
b100 Q
b1000 4
b10000 $
b10000 +
1(
1&
1%
#1700000
0%
#1710000
0=
b101 Q
b1100 7
b1100 H
b1100 I
b0 4
b0 $
b0 +
0(
0&
1%
#1720000
0%
#1730000
b1 Q
b1000 4
b10000 $
b10000 +
1(
1&
1%
#1740000
0%
#1750000
18
b11 Q
b0 4
b0 $
b0 +
0(
0&
1%
#1760000
0%
#1770000
1=
08
b1100110100000000000000000000000 @
b1100110100000000000000000000000 C
b100 Q
b1000 4
b10000 $
b10000 +
1(
1&
1%
#1780000
0%
#1790000
0=
b101 Q
b1011 7
b1011 H
b1011 I
b0 4
b0 $
b0 +
0(
0&
1%
#1800000
0%
#1810000
b1 Q
b1000 4
b10000 $
b10000 +
1(
1&
1%
#1820000
0%
#1830000
18
b11 Q
b0 4
b0 $
b0 +
0(
0&
1%
#1840000
0%
#1850000
1:
1=
08
b11001101000000000000000000000000 @
b11001101000000000000000000000000 C
b100 Q
b1000 4
b10000 $
b10000 +
1(
1&
1%
#1860000
0%
#1870000
0=
b101 Q
b1010 7
b1010 H
b1010 I
b0 4
b0 $
b0 +
0(
0&
1%
#1880000
0%
#1890000
b1 Q
b1000 4
b10000 $
b10000 +
1(
1&
1%
#1900000
0%
#1910000
18
b11 Q
b0 4
b0 $
b0 +
0(
0&
1%
#1920000
0%
#1930000
1=
08
b10011010000000000000000000000000 @
b10011010000000000000000000000000 C
b1 .
b1 6
b1 ?
b1 E
b1 F
b100 Q
b1000 4
b10000 $
b10000 +
1(
1&
1%
#1940000
0%
#1950000
0=
b101 Q
b1001 7
b1001 H
b1001 I
b0 4
b0 $
b0 +
0(
0&
1%
#1960000
0%
#1970000
b1 Q
b1000 4
b10000 $
b10000 +
1(
1&
1%
#1980000
0%
#1990000
18
b11 Q
b0 4
b0 $
b0 +
0(
0&
1%
#2000000
0%
#2010000
0:
1=
08
b110100000000000000000000000000 @
b110100000000000000000000000000 C
b11 .
b11 6
b11 ?
b11 E
b11 F
b100 Q
b1000 4
b10000 $
b10000 +
1(
1&
1%
#2020000
0%
#2030000
0=
b101 Q
b1000 7
b1000 H
b1000 I
b0 4
b0 $
b0 +
0(
0&
1%
#2040000
0%
#2050000
b1 Q
b1000 4
b10000 $
b10000 +
1(
1&
1%
#2060000
0%
#2070000
18
b11 Q
b0 4
b0 $
b0 +
0(
0&
1%
#2080000
0%
#2090000
1;
b1 9
b1 D
b1 G
1=
08
b1101000000000000000000000000000 @
b1101000000000000000000000000000 C
b110 .
b110 6
b110 ?
b110 E
b110 F
b100 Q
b1000 4
b10000 $
b10000 +
1(
1&
1%
#2100000
0%
#2110000
0=
b101 Q
b111 7
b111 H
b111 I
b0 4
b0 $
b0 +
0(
0&
1%
#2120000
0%
#2130000
b1 Q
b1000 4
b10000 $
b10000 +
1(
1&
1%
#2140000
0%
#2150000
1A
b10 Q
b0 4
b0 $
b0 +
0(
0&
1%
#2160000
0%
#2170000
18
0A
b1001 .
b1001 6
b1001 ?
b1001 E
b1001 F
b11 Q
b1000 4
b10000 $
b10000 +
1(
1&
1%
#2180000
0%
#2190000
1=
08
0;
b0 9
b0 D
b0 G
1:
b100 Q
b10010 .
b10010 6
b10010 ?
b10010 E
b10010 F
b11010000000000000000000000000000 @
b11010000000000000000000000000000 C
b0 4
b0 $
b0 +
0(
0&
1%
#2200000
0%
#2210000
0=
b110 7
b110 H
b110 I
b101 Q
b1000 4
b10000 $
b10000 +
1(
1&
1%
#2220000
0%
#2230000
b1 Q
b0 4
b0 $
b0 +
0(
0&
1%
#2240000
0%
#2250000
18
b11 Q
b1000 4
b10000 $
b10000 +
1(
1&
1%
#2260000
0%
#2270000
1=
08
1;
b1 9
b1 D
b1 G
b100 Q
b100101 .
b100101 6
b100101 ?
b100101 E
b100101 F
b10100000000000000000000000000000 @
b10100000000000000000000000000000 C
b0 4
b0 $
b0 +
0(
0&
1%
#2280000
0%
#2290000
0=
b101 7
b101 H
b101 I
b101 Q
b1000 4
b10000 $
b10000 +
1(
1&
1%
#2300000
0%
#2310000
b1 Q
b0 4
b0 $
b0 +
0(
0&
1%
#2320000
0%
#2330000
1A
b10 Q
b1000 4
b10000 $
b10000 +
1(
1&
1%
#2340000
0%
#2350000
18
0A
b11 Q
b101000 .
b101000 6
b101000 ?
b101000 E
b101000 F
b0 4
b0 $
b0 +
0(
0&
1%
#2360000
0%
#2370000
0:
b10 9
b10 D
b10 G
1=
08
b1000000000000000000000000000000 @
b1000000000000000000000000000000 C
b1010001 .
b1010001 6
b1010001 ?
b1010001 E
b1010001 F
b100 Q
b1000 4
b10000 $
b10000 +
1(
1&
1%
#2380000
0%
#2390000
0=
b101 Q
b100 7
b100 H
b100 I
b0 4
b0 $
b0 +
0(
0&
1%
#2400000
0%
#2410000
b1 Q
b1000 4
b10000 $
b10000 +
1(
1&
1%
#2420000
0%
#2430000
1A
b10 Q
b0 4
b0 $
b0 +
0(
0&
1%
#2440000
0%
#2450000
18
0A
b10000001 .
b10000001 6
b10000001 ?
b10000001 E
b10000001 F
b11 Q
b1000 4
b10000 $
b10000 +
1(
1&
1%
#2460000
0%
#2470000
1=
08
0;
b0 9
b0 D
b0 G
1:
b100 Q
b100000010 .
b100000010 6
b100000010 ?
b100000010 E
b100000010 F
b10000000000000000000000000000000 @
b10000000000000000000000000000000 C
b0 4
b0 $
b0 +
0(
0&
1%
#2480000
0%
#2490000
0=
b11 7
b11 H
b11 I
b101 Q
b1000 4
b10000 $
b10000 +
1(
1&
1%
#2500000
0%
#2510000
b1 Q
b0 4
b0 $
b0 +
0(
0&
1%
#2520000
0%
#2530000
18
b11 Q
b1000 4
b10000 $
b10000 +
1(
1&
1%
#2540000
0%
